[
  {
    "college_code": "isothermal",
    "term": "2026SU",
    "course_prefix": "ACA",
    "course_number": "122",
    "course_title": "College Transfer Success",
    "credits": 1,
    "crn": "ACA-122-500H1",
    "days": "T",
    "start_time": "8:05 AM",
    "end_time": "9:20 AM",
    "start_date": "2026-05-26",
    "location": "Main Campus",
    "campus": "MC",
    "mode": "in-person",
    "instructor": "Clay, S",
    "seats_open": 13,
    "seats_total": 15,
    "prerequisite_text": null,
    "prerequisite_courses": []
  },
  {
    "college_code": "isothermal",
    "term": "2026SU",
    "course_prefix": "ACA",
    "course_number": "122",
    "course_title": "College Transfer Success",
    "credits": 1,
    "crn": "ACA-122-700I1",
    "days": "",
    "start_time": "",
    "end_time": "",
    "start_date": "2026-05-26",
    "location": "Main Campus",
    "campus": "MC",
    "mode": "online",
    "instructor": "Clay, S",
    "seats_open": 0,
    "seats_total": 15,
    "prerequisite_text": null,
    "prerequisite_courses": []
  },
  {
    "college_code": "isothermal",
    "term": "2026SU",
    "course_prefix": "ACA",
    "course_number": "122",
    "course_title": "College Transfer Success",
    "credits": 1,
    "crn": "ACA-122-701I1",
    "days": "",
    "start_time": "",
    "end_time": "",
    "start_date": "2026-05-26",
    "location": "Main Campus",
    "campus": "MC",
    "mode": "online",
    "instructor": "Clay, S",
    "seats_open": 0,
    "seats_total": 15,
    "prerequisite_text": null,
    "prerequisite_courses": []
  },
  {
    "college_code": "isothermal",
    "term": "2026SU",
    "course_prefix": "ACA",
    "course_number": "122",
    "course_title": "College Transfer Success",
    "credits": 1,
    "crn": "ACA-122-702I1",
    "days": "",
    "start_time": "",
    "end_time": "",
    "start_date": "2026-05-26",
    "location": "Main Campus",
    "campus": "MC",
    "mode": "online",
    "instructor": "Smith, L",
    "seats_open": 1,
    "seats_total": 15,
    "prerequisite_text": null,
    "prerequisite_courses": []
  },
  {
    "college_code": "isothermal",
    "term": "2026SU",
    "course_prefix": "ACA",
    "course_number": "122",
    "course_title": "College Transfer Success",
    "credits": 1,
    "crn": "ACA-122-703I1",
    "days": "",
    "start_time": "",
    "end_time": "",
    "start_date": "2026-05-26",
    "location": "Main Campus",
    "campus": "MC",
    "mode": "online",
    "instructor": "Clay, S",
    "seats_open": 15,
    "seats_total": 15,
    "prerequisite_text": null,
    "prerequisite_courses": []
  },
  {
    "college_code": "isothermal",
    "term": "2026SU",
    "course_prefix": "ACC",
    "course_number": "120",
    "course_title": "Prin of Financial Accounting",
    "credits": 4,
    "crn": "ACC-120-700I1",
    "days": "",
    "start_time": "",
    "end_time": "",
    "start_date": "2026-05-26",
    "location": "Main Campus",
    "campus": "MC",
    "mode": "online",
    "instructor": "Childress, R",
    "seats_open": 10,
    "seats_total": 25,
    "prerequisite_text": null,
    "prerequisite_courses": []
  },
  {
    "college_code": "isothermal",
    "term": "2026SU",
    "course_prefix": "ACC",
    "course_number": "121",
    "course_title": "Prin of Managerial Accounting",
    "credits": 4,
    "crn": "ACC-121-700I1",
    "days": "",
    "start_time": "",
    "end_time": "",
    "start_date": "2026-05-26",
    "location": "Main Campus",
    "campus": "MC",
    "mode": "online",
    "instructor": "Childress, R",
    "seats_open": 9,
    "seats_total": 25,
    "prerequisite_text": null,
    "prerequisite_courses": []
  },
  {
    "college_code": "isothermal",
    "term": "2026SU",
    "course_prefix": "ACC",
    "course_number": "150",
    "course_title": "Accounting Software Appl",
    "credits": 2,
    "crn": "ACC-150-700I1",
    "days": "",
    "start_time": "",
    "end_time": "",
    "start_date": "2026-05-26",
    "location": "Main Campus",
    "campus": "MC",
    "mode": "online",
    "instructor": "Childress, R",
    "seats_open": 25,
    "seats_total": 25,
    "prerequisite_text": null,
    "prerequisite_courses": []
  },
  {
    "college_code": "isothermal",
    "term": "2026SU",
    "course_prefix": "AHR",
    "course_number": "110",
    "course_title": "Intro to Refrigeration",
    "credits": 5,
    "crn": "AHR-110-100W1",
    "days": "M W",
    "start_time": "5:00 PM",
    "end_time": "9:00 PM",
    "start_date": "2026-05-26",
    "location": "Main Campus",
    "campus": "MC",
    "mode": "in-person",
    "instructor": "Hollifield, M",
    "seats_open": 6,
    "seats_total": 12,
    "prerequisite_text": null,
    "prerequisite_courses": []
  },
  {
    "college_code": "isothermal",
    "term": "2026SU",
    "course_prefix": "ARC",
    "course_number": "112",
    "course_title": "Constr Matls & Methods",
    "credits": 4,
    "crn": "ARC-112-700I1",
    "days": "",
    "start_time": "",
    "end_time": "",
    "start_date": "2026-05-26",
    "location": "Main Campus",
    "campus": "MC",
    "mode": "online",
    "instructor": "Lyda, M",
    "seats_open": 15,
    "seats_total": 25,
    "prerequisite_text": null,
    "prerequisite_courses": []
  },
  {
    "college_code": "isothermal",
    "term": "2026SU",
    "course_prefix": "ART",
    "course_number": "111",
    "course_title": "Art Appreciation",
    "credits": 3,
    "crn": "ART-111-700I1",
    "days": "",
    "start_time": "",
    "end_time": "",
    "start_date": "2026-05-26",
    "location": "Main Campus",
    "campus": "MC",
    "mode": "online",
    "instructor": null,
    "seats_open": 0,
    "seats_total": 25,
    "prerequisite_text": null,
    "prerequisite_courses": []
  },
  {
    "college_code": "isothermal",
    "term": "2026SU",
    "course_prefix": "ART",
    "course_number": "115",
    "course_title": "Art History Survey II",
    "credits": 3,
    "crn": "ART-115-700I1",
    "days": "",
    "start_time": "",
    "end_time": "",
    "start_date": "2026-05-26",
    "location": "Main Campus",
    "campus": "MC",
    "mode": "online",
    "instructor": null,
    "seats_open": 13,
    "seats_total": 25,
    "prerequisite_text": null,
    "prerequisite_courses": []
  },
  {
    "college_code": "isothermal",
    "term": "2026SU",
    "course_prefix": "BIO",
    "course_number": "110",
    "course_title": "Principles of Biology",
    "credits": 4,
    "crn": "BIO-110-700I1",
    "days": "",
    "start_time": "",
    "end_time": "",
    "start_date": "2026-05-26",
    "location": "Main Campus",
    "campus": "MC",
    "mode": "online",
    "instructor": "Hoyle, N",
    "seats_open": 1,
    "seats_total": 30,
    "prerequisite_text": null,
    "prerequisite_courses": []
  },
  {
    "college_code": "isothermal",
    "term": "2026SU",
    "course_prefix": "BIO",
    "course_number": "168",
    "course_title": "Anatomy and Physiology I",
    "credits": 4,
    "crn": "BIO-168-700I1",
    "days": "",
    "start_time": "",
    "end_time": "",
    "start_date": "2026-05-26",
    "location": "Main Campus",
    "campus": "MC",
    "mode": "online",
    "instructor": "Schulte, J",
    "seats_open": 1,
    "seats_total": 25,
    "prerequisite_text": null,
    "prerequisite_courses": []
  },
  {
    "college_code": "isothermal",
    "term": "2026SU",
    "course_prefix": "BIO",
    "course_number": "169",
    "course_title": "Anatomy and Physiology II",
    "credits": 4,
    "crn": "BIO-169-700I1",
    "days": "",
    "start_time": "",
    "end_time": "",
    "start_date": "2026-05-26",
    "location": "Main Campus",
    "campus": "MC",
    "mode": "online",
    "instructor": "Bridges, A",
    "seats_open": 7,
    "seats_total": 25,
    "prerequisite_text": null,
    "prerequisite_courses": []
  },
  {
    "college_code": "isothermal",
    "term": "2026SU",
    "course_prefix": "BIO",
    "course_number": "275",
    "course_title": "Microbiology",
    "credits": 4,
    "crn": "BIO-275-700I1",
    "days": "",
    "start_time": "",
    "end_time": "",
    "start_date": "2026-05-26",
    "location": "Main Campus",
    "campus": "MC",
    "mode": "online",
    "instructor": "Watson, S",
    "seats_open": 4,
    "seats_total": 30,
    "prerequisite_text": null,
    "prerequisite_courses": []
  },
  {
    "college_code": "isothermal",
    "term": "2026SU",
    "course_prefix": "BIO",
    "course_number": "275",
    "course_title": "Microbiology",
    "credits": 4,
    "crn": "BIO-275-701I1",
    "days": "",
    "start_time": "",
    "end_time": "",
    "start_date": "2026-05-26",
    "location": "Main Campus",
    "campus": "MC",
    "mode": "online",
    "instructor": "Watson, S",
    "seats_open": 5,
    "seats_total": 30,
    "prerequisite_text": null,
    "prerequisite_courses": []
  },
  {
    "college_code": "isothermal",
    "term": "2026SU",
    "course_prefix": "BPT",
    "course_number": "235",
    "course_title": "Video Performance I",
    "credits": 2,
    "crn": "BPT-235-001W1",
    "days": "M W",
    "start_time": "8:35 AM",
    "end_time": "11:35 AM",
    "start_date": "2026-05-26",
    "location": "Main Campus",
    "campus": "MC",
    "mode": "in-person",
    "instructor": "Young, C",
    "seats_open": 11,
    "seats_total": 12,
    "prerequisite_text": null,
    "prerequisite_courses": []
  },
  {
    "college_code": "isothermal",
    "term": "2026SU",
    "course_prefix": "BUS",
    "course_number": "110",
    "course_title": "Introduction to Business",
    "credits": 3,
    "crn": "BUS-110-700I1",
    "days": "",
    "start_time": "",
    "end_time": "",
    "start_date": "2026-05-26",
    "location": "Main Campus",
    "campus": "MC",
    "mode": "online",
    "instructor": "Haney, R",
    "seats_open": 16,
    "seats_total": 25,
    "prerequisite_text": null,
    "prerequisite_courses": []
  },
  {
    "college_code": "isothermal",
    "term": "2026SU",
    "course_prefix": "BUS",
    "course_number": "125",
    "course_title": "Personal Finance",
    "credits": 3,
    "crn": "BUS-125-700I1",
    "days": "",
    "start_time": "",
    "end_time": "",
    "start_date": "2026-05-26",
    "location": "Main Campus",
    "campus": "MC",
    "mode": "online",
    "instructor": "Bland, J",
    "seats_open": 9,
    "seats_total": 25,
    "prerequisite_text": null,
    "prerequisite_courses": []
  },
  {
    "college_code": "isothermal",
    "term": "2026SU",
    "course_prefix": "BUS",
    "course_number": "137",
    "course_title": "Principles of Management",
    "credits": 3,
    "crn": "BUS-137-700I1",
    "days": "",
    "start_time": "",
    "end_time": "",
    "start_date": "2026-05-26",
    "location": "Main Campus",
    "campus": "MC",
    "mode": "online",
    "instructor": "Johnson, M",
    "seats_open": 14,
    "seats_total": 25,
    "prerequisite_text": null,
    "prerequisite_courses": []
  },
  {
    "college_code": "isothermal",
    "term": "2026SU",
    "course_prefix": "CHM",
    "course_number": "130",
    "course_title": "Gen, Org, & Biochemistry",
    "credits": 3,
    "crn": "CHM-130-700I1",
    "days": "",
    "start_time": "",
    "end_time": "",
    "start_date": "2026-05-26",
    "location": "Main Campus",
    "campus": "MC",
    "mode": "online",
    "instructor": "Hines, R",
    "seats_open": 21,
    "seats_total": 25,
    "prerequisite_text": null,
    "prerequisite_courses": []
  },
  {
    "college_code": "isothermal",
    "term": "2026SU",
    "course_prefix": "CHM",
    "course_number": "130A",
    "course_title": "Gen, Org, & Biochem Lab",
    "credits": 1,
    "crn": "CHM-130A-700I1",
    "days": "",
    "start_time": "",
    "end_time": "",
    "start_date": "2026-05-26",
    "location": "Main Campus",
    "campus": "MC",
    "mode": "online",
    "instructor": "Hines, R",
    "seats_open": 21,
    "seats_total": 25,
    "prerequisite_text": null,
    "prerequisite_courses": []
  },
  {
    "college_code": "isothermal",
    "term": "2026SU",
    "course_prefix": "CHM",
    "course_number": "151",
    "course_title": "General Chemistry I",
    "credits": 4,
    "crn": "CHM-151-700I1",
    "days": "",
    "start_time": "",
    "end_time": "",
    "start_date": "2026-05-26",
    "location": "Main Campus",
    "campus": "MC",
    "mode": "online",
    "instructor": "Dragan, N",
    "seats_open": 0,
    "seats_total": 25,
    "prerequisite_text": null,
    "prerequisite_courses": []
  },
  {
    "college_code": "isothermal",
    "term": "2026SU",
    "course_prefix": "CHM",
    "course_number": "152",
    "course_title": "General Chemistry II",
    "credits": 4,
    "crn": "CHM-152-700I1",
    "days": "",
    "start_time": "",
    "end_time": "",
    "start_date": "2026-05-26",
    "location": "Main Campus",
    "campus": "MC",
    "mode": "online",
    "instructor": "Dragan, N",
    "seats_open": 21,
    "seats_total": 25,
    "prerequisite_text": null,
    "prerequisite_courses": []
  },
  {
    "college_code": "isothermal",
    "term": "2026SU",
    "course_prefix": "CIS",
    "course_number": "110",
    "course_title": "Introduction to Computers",
    "credits": 3,
    "crn": "CIS-110-700I1",
    "days": "",
    "start_time": "",
    "end_time": "",
    "start_date": "2026-05-26",
    "location": "Main Campus",
    "campus": "MC",
    "mode": "online",
    "instructor": "Kilgo, S",
    "seats_open": 0,
    "seats_total": 25,
    "prerequisite_text": null,
    "prerequisite_courses": []
  },
  {
    "college_code": "isothermal",
    "term": "2026SU",
    "course_prefix": "CIS",
    "course_number": "110",
    "course_title": "Introduction to Computers",
    "credits": 3,
    "crn": "CIS-110-701I1",
    "days": "",
    "start_time": "",
    "end_time": "",
    "start_date": "2026-05-26",
    "location": "Main Campus",
    "campus": "MC",
    "mode": "online",
    "instructor": "Mitchell, K",
    "seats_open": 7,
    "seats_total": 25,
    "prerequisite_text": null,
    "prerequisite_courses": []
  },
  {
    "college_code": "isothermal",
    "term": "2026SU",
    "course_prefix": "CIV",
    "course_number": "125",
    "course_title": "Civil/Surveying CAD",
    "credits": 3,
    "crn": "CIV-125-700I1",
    "days": "",
    "start_time": "",
    "end_time": "",
    "start_date": "2026-05-26",
    "location": "Main Campus",
    "campus": "MC",
    "mode": "online",
    "instructor": "Hodge, B",
    "seats_open": 24,
    "seats_total": 25,
    "prerequisite_text": null,
    "prerequisite_courses": []
  },
  {
    "college_code": "isothermal",
    "term": "2026SU",
    "course_prefix": "CIV",
    "course_number": "240",
    "course_title": "Project Management",
    "credits": 3,
    "crn": "CIV-240-700I1",
    "days": "",
    "start_time": "",
    "end_time": "",
    "start_date": "2026-05-26",
    "location": "Main Campus",
    "campus": "MC",
    "mode": "online",
    "instructor": "Lyda, M",
    "seats_open": 18,
    "seats_total": 25,
    "prerequisite_text": null,
    "prerequisite_courses": []
  },
  {
    "college_code": "isothermal",
    "term": "2026SU",
    "course_prefix": "CMT",
    "course_number": "120",
    "course_title": "Codes and Inspections",
    "credits": 3,
    "crn": "CMT-120-700I1",
    "days": "",
    "start_time": "",
    "end_time": "",
    "start_date": "2026-05-26",
    "location": "Main Campus",
    "campus": "MC",
    "mode": "online",
    "instructor": "Lyda, M",
    "seats_open": 23,
    "seats_total": 25,
    "prerequisite_text": null,
    "prerequisite_courses": []
  },
  {
    "college_code": "isothermal",
    "term": "2026SU",
    "course_prefix": "COM",
    "course_number": "231",
    "course_title": "Public Speaking",
    "credits": 3,
    "crn": "COM-231-700I1",
    "days": "",
    "start_time": "",
    "end_time": "",
    "start_date": "2026-05-26",
    "location": "Main Campus",
    "campus": "MC",
    "mode": "online",
    "instructor": "Poole, K",
    "seats_open": 1,
    "seats_total": 25,
    "prerequisite_text": null,
    "prerequisite_courses": []
  },
  {
    "college_code": "isothermal",
    "term": "2026SU",
    "course_prefix": "COM",
    "course_number": "231",
    "course_title": "Public Speaking",
    "credits": 3,
    "crn": "COM-231-701I1",
    "days": "",
    "start_time": "",
    "end_time": "",
    "start_date": "2026-05-26",
    "location": "Main Campus",
    "campus": "MC",
    "mode": "online",
    "instructor": "Poole, K",
    "seats_open": 0,
    "seats_total": 25,
    "prerequisite_text": null,
    "prerequisite_courses": []
  },
  {
    "college_code": "isothermal",
    "term": "2026SU",
    "course_prefix": "COM",
    "course_number": "231",
    "course_title": "Public Speaking",
    "credits": 3,
    "crn": "COM-231-702I1",
    "days": "",
    "start_time": "",
    "end_time": "",
    "start_date": "2026-05-26",
    "location": "Main Campus",
    "campus": "MC",
    "mode": "online",
    "instructor": "Poole, K",
    "seats_open": 22,
    "seats_total": 25,
    "prerequisite_text": null,
    "prerequisite_courses": []
  },
  {
    "college_code": "isothermal",
    "term": "2026SU",
    "course_prefix": "COS",
    "course_number": "115",
    "course_title": "Cosmetology Concepts III",
    "credits": 4,
    "crn": "COS-115-740IF",
    "days": "",
    "start_time": "",
    "end_time": "",
    "start_date": "2026-05-26",
    "location": "Main Campus",
    "campus": "MC",
    "mode": "online",
    "instructor": "Harris, R, Jones, K",
    "seats_open": 13,
    "seats_total": 25,
    "prerequisite_text": null,
    "prerequisite_courses": []
  },
  {
    "college_code": "isothermal",
    "term": "2026SU",
    "course_prefix": "COS",
    "course_number": "116",
    "course_title": "Salon III",
    "credits": 4,
    "crn": "COS-116-040TF",
    "days": "M T W Th",
    "start_time": "8:00 AM",
    "end_time": "1:03 PM",
    "start_date": "2026-05-26",
    "location": "Main Campus",
    "campus": "MC",
    "mode": "in-person",
    "instructor": "Harris, R, Jones, K",
    "seats_open": 18,
    "seats_total": 30,
    "prerequisite_text": null,
    "prerequisite_courses": []
  },
  {
    "college_code": "isothermal",
    "term": "2026SU",
    "course_prefix": "COS",
    "course_number": "273",
    "course_title": "Instructor Concepts II",
    "credits": 5,
    "crn": "COS-273-740IF",
    "days": "",
    "start_time": "",
    "end_time": "",
    "start_date": "2026-05-26",
    "location": "Main Campus",
    "campus": "MC",
    "mode": "online",
    "instructor": "Jones, K",
    "seats_open": 0,
    "seats_total": 1,
    "prerequisite_text": null,
    "prerequisite_courses": []
  },
  {
    "college_code": "isothermal",
    "term": "2026SU",
    "course_prefix": "COS",
    "course_number": "274",
    "course_title": "Instructor Practicum II",
    "credits": 7,
    "crn": "COS-274-001WF",
    "days": "M T W Th",
    "start_time": "8:00 AM",
    "end_time": "2:11 PM",
    "start_date": "2026-05-26",
    "location": "Main Campus",
    "campus": "MC",
    "mode": "in-person",
    "instructor": "Jones, K",
    "seats_open": 0,
    "seats_total": 1,
    "prerequisite_text": null,
    "prerequisite_courses": []
  },
  {
    "college_code": "isothermal",
    "term": "2026SU",
    "course_prefix": "CSC",
    "course_number": "121",
    "course_title": "Python Programming",
    "credits": 3,
    "crn": "CSC-121-700I1",
    "days": "",
    "start_time": "",
    "end_time": "",
    "start_date": "2026-05-26",
    "location": "Main Campus",
    "campus": "MC",
    "mode": "online",
    "instructor": "Greene, T",
    "seats_open": 10,
    "seats_total": 25,
    "prerequisite_text": null,
    "prerequisite_courses": []
  },
  {
    "college_code": "isothermal",
    "term": "2026SU",
    "course_prefix": "CST",
    "course_number": "131",
    "course_title": "OSHA/Safety/Certification",
    "credits": 3,
    "crn": "CST-131-001H1",
    "days": "M",
    "start_time": "8:00 AM",
    "end_time": "9:20 AM",
    "start_date": "2026-05-26",
    "location": "Main Campus",
    "campus": "MC",
    "mode": "in-person",
    "instructor": "Lyda, M",
    "seats_open": 5,
    "seats_total": 15,
    "prerequisite_text": null,
    "prerequisite_courses": []
  },
  {
    "college_code": "isothermal",
    "term": "2026SU",
    "course_prefix": "CST",
    "course_number": "221",
    "course_title": "Statics/Structures",
    "credits": 4,
    "crn": "CST-221-700I1",
    "days": "",
    "start_time": "",
    "end_time": "",
    "start_date": "2026-05-26",
    "location": "Main Campus",
    "campus": "MC",
    "mode": "online",
    "instructor": "Lyda, M",
    "seats_open": 18,
    "seats_total": 25,
    "prerequisite_text": null,
    "prerequisite_courses": []
  },
  {
    "college_code": "isothermal",
    "term": "2026SU",
    "course_prefix": "CST",
    "course_number": "244",
    "course_title": "Sustainable Bldg Design",
    "credits": 3,
    "crn": "CST-244-700I1",
    "days": "",
    "start_time": "",
    "end_time": "",
    "start_date": "2026-05-26",
    "location": "Main Campus",
    "campus": "MC",
    "mode": "online",
    "instructor": "Lyda, M",
    "seats_open": 22,
    "seats_total": 25,
    "prerequisite_text": null,
    "prerequisite_courses": []
  },
  {
    "college_code": "isothermal",
    "term": "2026SU",
    "course_prefix": "CTS",
    "course_number": "130",
    "course_title": "Spreadsheet",
    "credits": 3,
    "crn": "CTS-130-700I1",
    "days": "",
    "start_time": "",
    "end_time": "",
    "start_date": "2026-05-26",
    "location": "Main Campus",
    "campus": "MC",
    "mode": "online",
    "instructor": "Johnson, M",
    "seats_open": 0,
    "seats_total": 25,
    "prerequisite_text": null,
    "prerequisite_courses": []
  },
  {
    "college_code": "isothermal",
    "term": "2026SU",
    "course_prefix": "CTS",
    "course_number": "130",
    "course_title": "Spreadsheet",
    "credits": 3,
    "crn": "CTS-130-701I1",
    "days": "",
    "start_time": "",
    "end_time": "",
    "start_date": "2026-05-26",
    "location": "Main Campus",
    "campus": "MC",
    "mode": "online",
    "instructor": "Johnson, M",
    "seats_open": 19,
    "seats_total": 25,
    "prerequisite_text": null,
    "prerequisite_courses": []
  },
  {
    "college_code": "isothermal",
    "term": "2026SU",
    "course_prefix": "DEN",
    "course_number": "107",
    "course_title": "Clinical Practice II",
    "credits": 5,
    "crn": "DEN-107-040WF",
    "days": "Th",
    "start_time": "2:00 PM",
    "end_time": "3:20 PM",
    "start_date": "2026-05-26",
    "location": "Main Campus",
    "campus": "MC",
    "mode": "in-person",
    "instructor": "Jenkins, S",
    "seats_open": 24,
    "seats_total": 24,
    "prerequisite_text": null,
    "prerequisite_courses": []
  },
  {
    "college_code": "isothermal",
    "term": "2026SU",
    "course_prefix": "DEN",
    "course_number": "140",
    "course_title": "Dental Hygiene Theory II",
    "credits": 2,
    "crn": "DEN-140-040WF",
    "days": "T",
    "start_time": "7:30 PM",
    "end_time": "8:42 PM",
    "start_date": "2026-05-26",
    "location": "Main Campus",
    "campus": "MC",
    "mode": "in-person",
    "instructor": "Jenkins, S",
    "seats_open": 10,
    "seats_total": 10,
    "prerequisite_text": null,
    "prerequisite_courses": []
  },
  {
    "college_code": "isothermal",
    "term": "2026SU",
    "course_prefix": "DEN",
    "course_number": "141",
    "course_title": "Dental Hygiene Clinic II",
    "credits": 2,
    "crn": "DEN-141-040TF",
    "days": "W",
    "start_time": "7:30 AM",
    "end_time": "1:30 PM",
    "start_date": "2026-05-26",
    "location": "Main Campus",
    "campus": "MC",
    "mode": "in-person",
    "instructor": "Jenkins, S",
    "seats_open": 5,
    "seats_total": 5,
    "prerequisite_text": null,
    "prerequisite_courses": []
  },
  {
    "college_code": "isothermal",
    "term": "2026SU",
    "course_prefix": "DEN",
    "course_number": "141",
    "course_title": "Dental Hygiene Clinic II",
    "credits": 2,
    "crn": "DEN-141-041TF",
    "days": "Th",
    "start_time": "7:30 AM",
    "end_time": "12:30 PM",
    "start_date": "2026-05-26",
    "location": "Main Campus",
    "campus": "MC",
    "mode": "in-person",
    "instructor": "Jenkins, S",
    "seats_open": 5,
    "seats_total": 5,
    "prerequisite_text": null,
    "prerequisite_courses": []
  },
  {
    "college_code": "isothermal",
    "term": "2026SU",
    "course_prefix": "DEN",
    "course_number": "224",
    "course_title": "Materials and Procedures",
    "credits": 2,
    "crn": "DEN-224-040WF",
    "days": "F",
    "start_time": "3:30 PM",
    "end_time": "4:30 PM",
    "start_date": "2026-05-26",
    "location": "Main Campus",
    "campus": "MC",
    "mode": "in-person",
    "instructor": "Jenkins, S, Bailey, M, Henson, K",
    "seats_open": 0,
    "seats_total": 10,
    "prerequisite_text": null,
    "prerequisite_courses": []
  },
  {
    "college_code": "isothermal",
    "term": "2026SU",
    "course_prefix": "DFT",
    "course_number": "121",
    "course_title": "Intro to GD&T",
    "credits": 2,
    "crn": "DFT-121-700I1",
    "days": "",
    "start_time": "",
    "end_time": "",
    "start_date": "2026-05-26",
    "location": "Main Campus",
    "campus": "MC",
    "mode": "online",
    "instructor": "Hodge, B",
    "seats_open": 23,
    "seats_total": 25,
    "prerequisite_text": null,
    "prerequisite_courses": []
  },
  {
    "college_code": "isothermal",
    "term": "2026SU",
    "course_prefix": "DFT",
    "course_number": "154",
    "course_title": "Intro Solid Modeling",
    "credits": 3,
    "crn": "DFT-154-700I1",
    "days": "",
    "start_time": "",
    "end_time": "",
    "start_date": "2026-05-26",
    "location": "Main Campus",
    "campus": "MC",
    "mode": "online",
    "instructor": "Hodge, B",
    "seats_open": 8,
    "seats_total": 25,
    "prerequisite_text": null,
    "prerequisite_courses": []
  },
  {
    "college_code": "isothermal",
    "term": "2026SU",
    "course_prefix": "DFT",
    "course_number": "254",
    "course_title": "Intermed Solid Model/Render",
    "credits": 3,
    "crn": "DFT-254-700I1",
    "days": "",
    "start_time": "",
    "end_time": "",
    "start_date": "2026-05-26",
    "location": "Main Campus",
    "campus": "MC",
    "mode": "online",
    "instructor": "Hodge, B",
    "seats_open": 23,
    "seats_total": 25,
    "prerequisite_text": null,
    "prerequisite_courses": []
  },
  {
    "college_code": "isothermal",
    "term": "2026SU",
    "course_prefix": "ECO",
    "course_number": "251",
    "course_title": "Prin of Microeconomics",
    "credits": 3,
    "crn": "ECO-251-700I1",
    "days": "",
    "start_time": "",
    "end_time": "",
    "start_date": "2026-05-26",
    "location": "Main Campus",
    "campus": "MC",
    "mode": "online",
    "instructor": "Bland, J",
    "seats_open": 0,
    "seats_total": 25,
    "prerequisite_text": null,
    "prerequisite_courses": []
  },
  {
    "college_code": "isothermal",
    "term": "2026SU",
    "course_prefix": "ECO",
    "course_number": "251",
    "course_title": "Prin of Microeconomics",
    "credits": 3,
    "crn": "ECO-251-701I1",
    "days": "",
    "start_time": "",
    "end_time": "",
    "start_date": "2026-05-26",
    "location": "Main Campus",
    "campus": "MC",
    "mode": "online",
    "instructor": "Bland, J",
    "seats_open": 13,
    "seats_total": 25,
    "prerequisite_text": null,
    "prerequisite_courses": []
  },
  {
    "college_code": "isothermal",
    "term": "2026SU",
    "course_prefix": "ECO",
    "course_number": "252",
    "course_title": "Prin of Macroeconomics",
    "credits": 3,
    "crn": "ECO-252-700I1",
    "days": "",
    "start_time": "",
    "end_time": "",
    "start_date": "2026-05-26",
    "location": "Main Campus",
    "campus": "MC",
    "mode": "online",
    "instructor": "Bland, J",
    "seats_open": 6,
    "seats_total": 25,
    "prerequisite_text": null,
    "prerequisite_courses": []
  },
  {
    "college_code": "isothermal",
    "term": "2026SU",
    "course_prefix": "EGR",
    "course_number": "250",
    "course_title": "Statics/Strength of Mater",
    "credits": 5,
    "crn": "EGR-250-001H1",
    "days": "Th",
    "start_time": "8:00 AM",
    "end_time": "11:00 AM",
    "start_date": "2026-05-26",
    "location": "Main Campus",
    "campus": "MC",
    "mode": "in-person",
    "instructor": "Roach, C",
    "seats_open": 19,
    "seats_total": 20,
    "prerequisite_text": null,
    "prerequisite_courses": []
  },
  {
    "college_code": "isothermal",
    "term": "2026SU",
    "course_prefix": "ELC",
    "course_number": "115",
    "course_title": "Industrial Wiring",
    "credits": 4,
    "crn": "ELC-115-040TF",
    "days": "M W",
    "start_time": "9:00 AM",
    "end_time": "10:25 AM",
    "start_date": "2026-05-26",
    "location": "Main Campus",
    "campus": "MC",
    "mode": "in-person",
    "instructor": null,
    "seats_open": 12,
    "seats_total": 16,
    "prerequisite_text": null,
    "prerequisite_courses": []
  },
  {
    "college_code": "isothermal",
    "term": "2026SU",
    "course_prefix": "ELC",
    "course_number": "115",
    "course_title": "Industrial Wiring",
    "credits": 4,
    "crn": "ELC-115-140TF",
    "days": "M W",
    "start_time": "6:00 PM",
    "end_time": "7:25 PM",
    "start_date": "2026-05-26",
    "location": "Main Campus",
    "campus": "MC",
    "mode": "in-person",
    "instructor": "Gibert, W",
    "seats_open": 7,
    "seats_total": 16,
    "prerequisite_text": null,
    "prerequisite_courses": []
  },
  {
    "college_code": "isothermal",
    "term": "2026SU",
    "course_prefix": "ELN",
    "course_number": "231",
    "course_title": "Industrial Controls",
    "credits": 3,
    "crn": "ELN-231-040TF",
    "days": "T Th",
    "start_time": "9:00 AM",
    "end_time": "10:25 AM",
    "start_date": "2026-05-26",
    "location": "Main Campus",
    "campus": "MC",
    "mode": "in-person",
    "instructor": null,
    "seats_open": 12,
    "seats_total": 16,
    "prerequisite_text": null,
    "prerequisite_courses": []
  },
  {
    "college_code": "isothermal",
    "term": "2026SU",
    "course_prefix": "ELN",
    "course_number": "231",
    "course_title": "Industrial Controls",
    "credits": 3,
    "crn": "ELN-231-140TF",
    "days": "T Th",
    "start_time": "6:00 PM",
    "end_time": "7:25 PM",
    "start_date": "2026-05-26",
    "location": "Main Campus",
    "campus": "MC",
    "mode": "in-person",
    "instructor": null,
    "seats_open": 12,
    "seats_total": 16,
    "prerequisite_text": null,
    "prerequisite_courses": []
  },
  {
    "college_code": "isothermal",
    "term": "2026SU",
    "course_prefix": "ENG",
    "course_number": "045",
    "course_title": "English Skills Support",
    "credits": 2,
    "crn": "ENG-045-500I1",
    "days": "",
    "start_time": "",
    "end_time": "",
    "start_date": "2026-05-26",
    "location": "Main Campus",
    "campus": "MC",
    "mode": "online",
    "instructor": null,
    "seats_open": 0,
    "seats_total": 15,
    "prerequisite_text": null,
    "prerequisite_courses": []
  },
  {
    "college_code": "isothermal",
    "term": "2026SU",
    "course_prefix": "ENG",
    "course_number": "045",
    "course_title": "English Skills Support",
    "credits": 2,
    "crn": "ENG-045-501I1",
    "days": "",
    "start_time": "",
    "end_time": "",
    "start_date": "2026-05-26",
    "location": "Main Campus",
    "campus": "MC",
    "mode": "online",
    "instructor": "Morgan, M",
    "seats_open": 0,
    "seats_total": 15,
    "prerequisite_text": null,
    "prerequisite_courses": []
  },
  {
    "college_code": "isothermal",
    "term": "2026SU",
    "course_prefix": "ENG",
    "course_number": "111",
    "course_title": "Writing and Inquiry",
    "credits": 3,
    "crn": "ENG-111-500I1",
    "days": "",
    "start_time": "",
    "end_time": "",
    "start_date": "2026-05-26",
    "location": "Main Campus",
    "campus": "MC",
    "mode": "online",
    "instructor": null,
    "seats_open": 0,
    "seats_total": 15,
    "prerequisite_text": null,
    "prerequisite_courses": []
  },
  {
    "college_code": "isothermal",
    "term": "2026SU",
    "course_prefix": "ENG",
    "course_number": "111",
    "course_title": "Writing and Inquiry",
    "credits": 3,
    "crn": "ENG-111-501I1",
    "days": "",
    "start_time": "",
    "end_time": "",
    "start_date": "2026-05-26",
    "location": "Main Campus",
    "campus": "MC",
    "mode": "online",
    "instructor": "Morgan, M",
    "seats_open": 0,
    "seats_total": 15,
    "prerequisite_text": null,
    "prerequisite_courses": []
  },
  {
    "college_code": "isothermal",
    "term": "2026SU",
    "course_prefix": "ENG",
    "course_number": "111",
    "course_title": "Writing and Inquiry",
    "credits": 3,
    "crn": "ENG-111-700I1",
    "days": "",
    "start_time": "",
    "end_time": "",
    "start_date": "2026-05-26",
    "location": "Main Campus",
    "campus": "MC",
    "mode": "online",
    "instructor": "Humphries, M",
    "seats_open": 0,
    "seats_total": 10,
    "prerequisite_text": null,
    "prerequisite_courses": []
  },
  {
    "college_code": "isothermal",
    "term": "2026SU",
    "course_prefix": "ENG",
    "course_number": "111",
    "course_title": "Writing and Inquiry",
    "credits": 3,
    "crn": "ENG-111-701I1",
    "days": "",
    "start_time": "",
    "end_time": "",
    "start_date": "2026-05-26",
    "location": "Main Campus",
    "campus": "MC",
    "mode": "online",
    "instructor": "Morgan, M",
    "seats_open": 0,
    "seats_total": 10,
    "prerequisite_text": null,
    "prerequisite_courses": []
  },
  {
    "college_code": "isothermal",
    "term": "2026SU",
    "course_prefix": "ENG",
    "course_number": "112",
    "course_title": "Writing/Research in the Disc",
    "credits": 3,
    "crn": "ENG-112-700I1",
    "days": "",
    "start_time": "",
    "end_time": "",
    "start_date": "2026-05-26",
    "location": "Main Campus",
    "campus": "MC",
    "mode": "online",
    "instructor": "Burris, J",
    "seats_open": 2,
    "seats_total": 25,
    "prerequisite_text": null,
    "prerequisite_courses": []
  },
  {
    "college_code": "isothermal",
    "term": "2026SU",
    "course_prefix": "ENG",
    "course_number": "112",
    "course_title": "Writing/Research in the Disc",
    "credits": 3,
    "crn": "ENG-112-701I1",
    "days": "",
    "start_time": "",
    "end_time": "",
    "start_date": "2026-05-26",
    "location": "Main Campus",
    "campus": "MC",
    "mode": "online",
    "instructor": "Burris, J",
    "seats_open": 15,
    "seats_total": 25,
    "prerequisite_text": null,
    "prerequisite_courses": []
  },
  {
    "college_code": "isothermal",
    "term": "2026SU",
    "course_prefix": "ENG",
    "course_number": "231",
    "course_title": "American Literature I",
    "credits": 3,
    "crn": "ENG-231-700I1",
    "days": "",
    "start_time": "",
    "end_time": "",
    "start_date": "2026-05-26",
    "location": "Main Campus",
    "campus": "MC",
    "mode": "online",
    "instructor": "Burris, J",
    "seats_open": 6,
    "seats_total": 25,
    "prerequisite_text": null,
    "prerequisite_courses": []
  },
  {
    "college_code": "isothermal",
    "term": "2026SU",
    "course_prefix": "EQU",
    "course_number": "211",
    "course_title": "Horse Farm Mgmt I",
    "credits": 6,
    "crn": "EQU-211-740IF",
    "days": "",
    "start_time": "",
    "end_time": "",
    "start_date": "2026-05-26",
    "location": "Main Campus",
    "campus": "MC",
    "mode": "online",
    "instructor": "Higgins, L",
    "seats_open": 20,
    "seats_total": 25,
    "prerequisite_text": null,
    "prerequisite_courses": []
  },
  {
    "college_code": "isothermal",
    "term": "2026SU",
    "course_prefix": "HIS",
    "course_number": "111",
    "course_title": "World Civilizations I",
    "credits": 3,
    "crn": "HIS-111-700I1",
    "days": "",
    "start_time": "",
    "end_time": "",
    "start_date": "2026-05-26",
    "location": "Main Campus",
    "campus": "MC",
    "mode": "online",
    "instructor": "Parker, B",
    "seats_open": 18,
    "seats_total": 25,
    "prerequisite_text": null,
    "prerequisite_courses": []
  },
  {
    "college_code": "isothermal",
    "term": "2026SU",
    "course_prefix": "HIS",
    "course_number": "112",
    "course_title": "World Civilizations II",
    "credits": 3,
    "crn": "HIS-112-700I1",
    "days": "",
    "start_time": "",
    "end_time": "",
    "start_date": "2026-05-26",
    "location": "Main Campus",
    "campus": "MC",
    "mode": "online",
    "instructor": "Parker, B",
    "seats_open": 21,
    "seats_total": 25,
    "prerequisite_text": null,
    "prerequisite_courses": []
  },
  {
    "college_code": "isothermal",
    "term": "2026SU",
    "course_prefix": "HIS",
    "course_number": "131",
    "course_title": "American History I",
    "credits": 3,
    "crn": "HIS-131-700I1",
    "days": "",
    "start_time": "",
    "end_time": "",
    "start_date": "2026-05-26",
    "location": "Main Campus",
    "campus": "MC",
    "mode": "online",
    "instructor": "Parker, B",
    "seats_open": 11,
    "seats_total": 25,
    "prerequisite_text": null,
    "prerequisite_courses": []
  },
  {
    "college_code": "isothermal",
    "term": "2026SU",
    "course_prefix": "HUM",
    "course_number": "115",
    "course_title": "Critical Thinking",
    "credits": 3,
    "crn": "HUM-115-700I1",
    "days": "",
    "start_time": "",
    "end_time": "",
    "start_date": "2026-05-26",
    "location": "Main Campus",
    "campus": "MC",
    "mode": "online",
    "instructor": "Humphries, M",
    "seats_open": 0,
    "seats_total": 25,
    "prerequisite_text": null,
    "prerequisite_courses": []
  },
  {
    "college_code": "isothermal",
    "term": "2026SU",
    "course_prefix": "HUM",
    "course_number": "230",
    "course_title": "Leadership Development",
    "credits": 3,
    "crn": "HUM-230-700I1",
    "days": "",
    "start_time": "",
    "end_time": "",
    "start_date": "2026-05-26",
    "location": "Main Campus",
    "campus": "MC",
    "mode": "online",
    "instructor": "Burris, J",
    "seats_open": 7,
    "seats_total": 25,
    "prerequisite_text": null,
    "prerequisite_courses": []
  },
  {
    "college_code": "isothermal",
    "term": "2026SU",
    "course_prefix": "HYD",
    "course_number": "110",
    "course_title": "Hydraulics/Pneumatics I",
    "credits": 3,
    "crn": "HYD-110-001W1",
    "days": "W",
    "start_time": "8:00 AM",
    "end_time": "10:00 AM",
    "start_date": "2026-05-26",
    "location": "Main Campus",
    "campus": "MC",
    "mode": "in-person",
    "instructor": "Roach, C",
    "seats_open": 16,
    "seats_total": 20,
    "prerequisite_text": null,
    "prerequisite_courses": []
  },
  {
    "college_code": "isothermal",
    "term": "2026SU",
    "course_prefix": "ISC",
    "course_number": "121",
    "course_title": "Envir Health & Safety",
    "credits": 3,
    "crn": "ISC-121-700I1",
    "days": "",
    "start_time": "",
    "end_time": "",
    "start_date": "2026-05-26",
    "location": "Main Campus",
    "campus": "MC",
    "mode": "online",
    "instructor": "Roach, C",
    "seats_open": 18,
    "seats_total": 25,
    "prerequisite_text": null,
    "prerequisite_courses": []
  },
  {
    "college_code": "isothermal",
    "term": "2026SU",
    "course_prefix": "MAC",
    "course_number": "113",
    "course_title": "Machining Technology III",
    "credits": 6,
    "crn": "MAC-113-001W1",
    "days": "M T",
    "start_time": "9:00 AM",
    "end_time": "9:56 AM",
    "start_date": "2026-05-26",
    "location": "Main Campus",
    "campus": "MC",
    "mode": "in-person",
    "instructor": "Waters, J",
    "seats_open": 7,
    "seats_total": 8,
    "prerequisite_text": null,
    "prerequisite_courses": []
  },
  {
    "college_code": "isothermal",
    "term": "2026SU",
    "course_prefix": "MAC",
    "course_number": "122",
    "course_title": "CNC Turning",
    "credits": 2,
    "crn": "MAC-122-001W1",
    "days": "W",
    "start_time": "12:01 PM",
    "end_time": "12:56 PM",
    "start_date": "2026-05-26",
    "location": "Main Campus",
    "campus": "MC",
    "mode": "in-person",
    "instructor": "Waters, J",
    "seats_open": 6,
    "seats_total": 8,
    "prerequisite_text": null,
    "prerequisite_courses": []
  },
  {
    "college_code": "isothermal",
    "term": "2026SU",
    "course_prefix": "MAC",
    "course_number": "126",
    "course_title": "CNC Metal Fabrication",
    "credits": 2,
    "crn": "MAC-126-001W1",
    "days": "W",
    "start_time": "8:00 AM",
    "end_time": "9:20 AM",
    "start_date": "2026-05-26",
    "location": "Main Campus",
    "campus": "MC",
    "mode": "in-person",
    "instructor": "Waters, J",
    "seats_open": 7,
    "seats_total": 8,
    "prerequisite_text": null,
    "prerequisite_courses": []
  },
  {
    "college_code": "isothermal",
    "term": "2026SU",
    "course_prefix": "MAT",
    "course_number": "025",
    "course_title": "Concepts of Essential Math/Sta",
    "credits": 3,
    "crn": "MAT-025-500W1",
    "days": "T Th",
    "start_time": "8:05 AM",
    "end_time": "9:20 AM",
    "start_date": "2026-05-26",
    "location": "Main Campus",
    "campus": "MC",
    "mode": "in-person",
    "instructor": "Laughter, D",
    "seats_open": 13,
    "seats_total": 15,
    "prerequisite_text": null,
    "prerequisite_courses": []
  },
  {
    "college_code": "isothermal",
    "term": "2026SU",
    "course_prefix": "MAT",
    "course_number": "025",
    "course_title": "Concepts of Essential Math/Sta",
    "credits": 3,
    "crn": "MAT-025-550I1",
    "days": "",
    "start_time": "",
    "end_time": "",
    "start_date": "2026-05-26",
    "location": "Main Campus",
    "campus": "MC",
    "mode": "online",
    "instructor": "Spratt, K",
    "seats_open": 0,
    "seats_total": 15,
    "prerequisite_text": null,
    "prerequisite_courses": []
  },
  {
    "college_code": "isothermal",
    "term": "2026SU",
    "course_prefix": "MAT",
    "course_number": "035",
    "course_title": "Concepts of Algebra",
    "credits": 3,
    "crn": "MAT-035-500W1",
    "days": "T Th",
    "start_time": "8:05 AM",
    "end_time": "9:20 AM",
    "start_date": "2026-05-26",
    "location": "Main Campus",
    "campus": "MC",
    "mode": "in-person",
    "instructor": "Laughter, D",
    "seats_open": 15,
    "seats_total": 15,
    "prerequisite_text": null,
    "prerequisite_courses": []
  },
  {
    "college_code": "isothermal",
    "term": "2026SU",
    "course_prefix": "MAT",
    "course_number": "035",
    "course_title": "Concepts of Algebra",
    "credits": 3,
    "crn": "MAT-035-550I1",
    "days": "",
    "start_time": "",
    "end_time": "",
    "start_date": "2026-05-26",
    "location": "Main Campus",
    "campus": "MC",
    "mode": "online",
    "instructor": "Spratt, K",
    "seats_open": 15,
    "seats_total": 15,
    "prerequisite_text": null,
    "prerequisite_courses": []
  },
  {
    "college_code": "isothermal",
    "term": "2026SU",
    "course_prefix": "MAT",
    "course_number": "110",
    "course_title": "Math Measurement & Literacy",
    "credits": 3,
    "crn": "MAT-110-700I1",
    "days": "",
    "start_time": "",
    "end_time": "",
    "start_date": "2026-05-26",
    "location": "Main Campus",
    "campus": "MC",
    "mode": "online",
    "instructor": "Spratt, K",
    "seats_open": 4,
    "seats_total": 30,
    "prerequisite_text": null,
    "prerequisite_courses": []
  },
  {
    "college_code": "isothermal",
    "term": "2026SU",
    "course_prefix": "MAT",
    "course_number": "143",
    "course_title": "Quantitative Literacy",
    "credits": 3,
    "crn": "MAT-143-700I1",
    "days": "",
    "start_time": "",
    "end_time": "",
    "start_date": "2026-05-26",
    "location": "Main Campus",
    "campus": "MC",
    "mode": "online",
    "instructor": "Roberts, N",
    "seats_open": 20,
    "seats_total": 25,
    "prerequisite_text": null,
    "prerequisite_courses": []
  },
  {
    "college_code": "isothermal",
    "term": "2026SU",
    "course_prefix": "MAT",
    "course_number": "152",
    "course_title": "Statistical Methods I",
    "credits": 4,
    "crn": "MAT-152-700I1",
    "days": "",
    "start_time": "",
    "end_time": "",
    "start_date": "2026-05-26",
    "location": "Main Campus",
    "campus": "MC",
    "mode": "online",
    "instructor": "Ireland, C",
    "seats_open": 8,
    "seats_total": 25,
    "prerequisite_text": null,
    "prerequisite_courses": []
  },
  {
    "college_code": "isothermal",
    "term": "2026SU",
    "course_prefix": "MAT",
    "course_number": "171",
    "course_title": "Precalculus Algebra",
    "credits": 4,
    "crn": "MAT-171-700I1",
    "days": "",
    "start_time": "",
    "end_time": "",
    "start_date": "2026-05-26",
    "location": "Main Campus",
    "campus": "MC",
    "mode": "online",
    "instructor": "Roberts, N",
    "seats_open": 8,
    "seats_total": 25,
    "prerequisite_text": null,
    "prerequisite_courses": []
  },
  {
    "college_code": "isothermal",
    "term": "2026SU",
    "course_prefix": "MAT",
    "course_number": "172",
    "course_title": "Precalculus Trigonometry",
    "credits": 4,
    "crn": "MAT-172-700I1",
    "days": "",
    "start_time": "",
    "end_time": "",
    "start_date": "2026-05-26",
    "location": "Main Campus",
    "campus": "MC",
    "mode": "online",
    "instructor": "Ireland, C",
    "seats_open": 19,
    "seats_total": 25,
    "prerequisite_text": null,
    "prerequisite_courses": []
  },
  {
    "college_code": "isothermal",
    "term": "2026SU",
    "course_prefix": "MAT",
    "course_number": "271",
    "course_title": "Calculus I",
    "credits": 4,
    "crn": "MAT-271-700I1",
    "days": "",
    "start_time": "",
    "end_time": "",
    "start_date": "2026-05-26",
    "location": "Main Campus",
    "campus": "MC",
    "mode": "online",
    "instructor": "Petit, A",
    "seats_open": 18,
    "seats_total": 25,
    "prerequisite_text": null,
    "prerequisite_courses": []
  },
  {
    "college_code": "isothermal",
    "term": "2026SU",
    "course_prefix": "MEC",
    "course_number": "270",
    "course_title": "Machine Design",
    "credits": 4,
    "crn": "MEC-270-001W1",
    "days": "T",
    "start_time": "8:00 AM",
    "end_time": "9:30 AM",
    "start_date": "2026-05-26",
    "location": "Main Campus",
    "campus": "MC",
    "mode": "in-person",
    "instructor": "Roach, C",
    "seats_open": 17,
    "seats_total": 20,
    "prerequisite_text": null,
    "prerequisite_courses": []
  },
  {
    "college_code": "isothermal",
    "term": "2026SU",
    "course_prefix": "MEC",
    "course_number": "271",
    "course_title": "Machine Design Project",
    "credits": 1,
    "crn": "MEC-271-001W1",
    "days": "T",
    "start_time": "1:01 PM",
    "end_time": "4:00 PM",
    "start_date": "2026-05-26",
    "location": "Main Campus",
    "campus": "MC",
    "mode": "in-person",
    "instructor": "Roach, C",
    "seats_open": 17,
    "seats_total": 20,
    "prerequisite_text": null,
    "prerequisite_courses": []
  },
  {
    "college_code": "isothermal",
    "term": "2026SU",
    "course_prefix": "MNT",
    "course_number": "110",
    "course_title": "Intro to Maint Procedures",
    "credits": 2,
    "crn": "MNT-110-001W1",
    "days": "M",
    "start_time": "8:00 AM",
    "end_time": "9:00 AM",
    "start_date": "2026-05-26",
    "location": "Main Campus",
    "campus": "MC",
    "mode": "in-person",
    "instructor": "Roach, C",
    "seats_open": 16,
    "seats_total": 20,
    "prerequisite_text": null,
    "prerequisite_courses": []
  },
  {
    "college_code": "isothermal",
    "term": "2026SU",
    "course_prefix": "MUS",
    "course_number": "110",
    "course_title": "Music Appreciation",
    "credits": 3,
    "crn": "MUS-110-700I1",
    "days": "",
    "start_time": "",
    "end_time": "",
    "start_date": "2026-05-26",
    "location": "Main Campus",
    "campus": "MC",
    "mode": "online",
    "instructor": null,
    "seats_open": 15,
    "seats_total": 25,
    "prerequisite_text": null,
    "prerequisite_courses": []
  },
  {
    "college_code": "isothermal",
    "term": "2026SU",
    "course_prefix": "NUR",
    "course_number": "103",
    "course_title": "Practical Nursing III",
    "credits": 9,
    "crn": "NUR-103-001W1",
    "days": "M W",
    "start_time": "8:30 AM",
    "end_time": "12:45 PM",
    "start_date": "2026-05-26",
    "location": "Main Campus",
    "campus": "MC",
    "mode": "in-person",
    "instructor": "Cuthbertson, B",
    "seats_open": 12,
    "seats_total": 35,
    "prerequisite_text": null,
    "prerequisite_courses": []
  },
  {
    "college_code": "isothermal",
    "term": "2026SU",
    "course_prefix": "NUR",
    "course_number": "114",
    "course_title": "Holistic Health Concepts",
    "credits": 5,
    "crn": "NUR-114-001W1",
    "days": "T",
    "start_time": "9:00 AM",
    "end_time": "1:00 PM",
    "start_date": "2026-05-26",
    "location": "Main Campus",
    "campus": "MC",
    "mode": "in-person",
    "instructor": "Alley, L, Tate, A, Cuthbertson, B",
    "seats_open": 47,
    "seats_total": 65,
    "prerequisite_text": null,
    "prerequisite_courses": []
  },
  {
    "college_code": "isothermal",
    "term": "2026SU",
    "course_prefix": "PHI",
    "course_number": "215",
    "course_title": "Philosophical Issues",
    "credits": 3,
    "crn": "PHI-215-700I1",
    "days": "",
    "start_time": "",
    "end_time": "",
    "start_date": "2026-05-26",
    "location": "Main Campus",
    "campus": "MC",
    "mode": "online",
    "instructor": null,
    "seats_open": 15,
    "seats_total": 25,
    "prerequisite_text": null,
    "prerequisite_courses": []
  },
  {
    "college_code": "isothermal",
    "term": "2026SU",
    "course_prefix": "PHI",
    "course_number": "240",
    "course_title": "Introduction to Ethics",
    "credits": 3,
    "crn": "PHI-240-700I1",
    "days": "",
    "start_time": "",
    "end_time": "",
    "start_date": "2026-05-26",
    "location": "Main Campus",
    "campus": "MC",
    "mode": "online",
    "instructor": null,
    "seats_open": 11,
    "seats_total": 25,
    "prerequisite_text": null,
    "prerequisite_courses": []
  },
  {
    "college_code": "isothermal",
    "term": "2026SU",
    "course_prefix": "POL",
    "course_number": "120",
    "course_title": "American Government",
    "credits": 3,
    "crn": "POL-120-700I1",
    "days": "",
    "start_time": "",
    "end_time": "",
    "start_date": "2026-05-26",
    "location": "Main Campus",
    "campus": "MC",
    "mode": "online",
    "instructor": null,
    "seats_open": 16,
    "seats_total": 25,
    "prerequisite_text": null,
    "prerequisite_courses": []
  },
  {
    "college_code": "isothermal",
    "term": "2026SU",
    "course_prefix": "PSY",
    "course_number": "150",
    "course_title": "General Psychology",
    "credits": 3,
    "crn": "PSY-150-700I1",
    "days": "",
    "start_time": "",
    "end_time": "",
    "start_date": "2026-05-26",
    "location": "Main Campus",
    "campus": "MC",
    "mode": "online",
    "instructor": "Hamrick, J",
    "seats_open": 0,
    "seats_total": 25,
    "prerequisite_text": null,
    "prerequisite_courses": []
  },
  {
    "college_code": "isothermal",
    "term": "2026SU",
    "course_prefix": "PSY",
    "course_number": "150",
    "course_title": "General Psychology",
    "credits": 3,
    "crn": "PSY-150-701I1",
    "days": "",
    "start_time": "",
    "end_time": "",
    "start_date": "2026-05-26",
    "location": "Main Campus",
    "campus": "MC",
    "mode": "online",
    "instructor": "Hamrick, J",
    "seats_open": 8,
    "seats_total": 25,
    "prerequisite_text": null,
    "prerequisite_courses": []
  },
  {
    "college_code": "isothermal",
    "term": "2026SU",
    "course_prefix": "PSY",
    "course_number": "241",
    "course_title": "Developmental Psych",
    "credits": 3,
    "crn": "PSY-241-700I1",
    "days": "",
    "start_time": "",
    "end_time": "",
    "start_date": "2026-05-26",
    "location": "Main Campus",
    "campus": "MC",
    "mode": "online",
    "instructor": "Beall, J",
    "seats_open": 0,
    "seats_total": 25,
    "prerequisite_text": null,
    "prerequisite_courses": []
  },
  {
    "college_code": "isothermal",
    "term": "2026SU",
    "course_prefix": "PSY",
    "course_number": "241",
    "course_title": "Developmental Psych",
    "credits": 3,
    "crn": "PSY-241-701I1",
    "days": "",
    "start_time": "",
    "end_time": "",
    "start_date": "2026-05-26",
    "location": "Main Campus",
    "campus": "MC",
    "mode": "online",
    "instructor": "Beall, J",
    "seats_open": 21,
    "seats_total": 25,
    "prerequisite_text": null,
    "prerequisite_courses": []
  },
  {
    "college_code": "isothermal",
    "term": "2026SU",
    "course_prefix": "SOC",
    "course_number": "210",
    "course_title": "Introduction to Sociology",
    "credits": 3,
    "crn": "SOC-210-700I1",
    "days": "",
    "start_time": "",
    "end_time": "",
    "start_date": "2026-05-26",
    "location": "Main Campus",
    "campus": "MC",
    "mode": "online",
    "instructor": "Ellis, M",
    "seats_open": 0,
    "seats_total": 25,
    "prerequisite_text": null,
    "prerequisite_courses": []
  },
  {
    "college_code": "isothermal",
    "term": "2026SU",
    "course_prefix": "SOC",
    "course_number": "210",
    "course_title": "Introduction to Sociology",
    "credits": 3,
    "crn": "SOC-210-701I1",
    "days": "",
    "start_time": "",
    "end_time": "",
    "start_date": "2026-05-26",
    "location": "Main Campus",
    "campus": "MC",
    "mode": "online",
    "instructor": "Ellis, M",
    "seats_open": 20,
    "seats_total": 25,
    "prerequisite_text": null,
    "prerequisite_courses": []
  },
  {
    "college_code": "isothermal",
    "term": "2026SU",
    "course_prefix": "SOC",
    "course_number": "220",
    "course_title": "Social Problems",
    "credits": 3,
    "crn": "SOC-220-700I1",
    "days": "",
    "start_time": "",
    "end_time": "",
    "start_date": "2026-05-26",
    "location": "Main Campus",
    "campus": "MC",
    "mode": "online",
    "instructor": "Ellis, M",
    "seats_open": 7,
    "seats_total": 25,
    "prerequisite_text": null,
    "prerequisite_courses": []
  },
  {
    "college_code": "isothermal",
    "term": "2026SU",
    "course_prefix": "WBL",
    "course_number": "111",
    "course_title": "Work-Based Learning I",
    "credits": 1,
    "crn": "WBL-111-040CF",
    "days": "",
    "start_time": "",
    "end_time": "",
    "start_date": "2026-05-26",
    "location": "Main Campus",
    "campus": "MC",
    "mode": "in-person",
    "instructor": "Higgins, L",
    "seats_open": 3,
    "seats_total": 7,
    "prerequisite_text": null,
    "prerequisite_courses": []
  },
  {
    "college_code": "isothermal",
    "term": "2026SU",
    "course_prefix": "WLD",
    "course_number": "112",
    "course_title": "Basic Welding Processes",
    "credits": 2,
    "crn": "WLD-112-001T1",
    "days": "M T W Th",
    "start_time": "12:45 PM",
    "end_time": "1:10 PM",
    "start_date": "2026-05-26",
    "location": "Main Campus",
    "campus": "MC",
    "mode": "in-person",
    "instructor": null,
    "seats_open": 2,
    "seats_total": 10,
    "prerequisite_text": null,
    "prerequisite_courses": []
  },
  {
    "college_code": "isothermal",
    "term": "2026SU",
    "course_prefix": "WLD",
    "course_number": "141",
    "course_title": "Symbols & Specifications",
    "credits": 3,
    "crn": "WLD-141-001T1",
    "days": "T Th",
    "start_time": "8:00 AM",
    "end_time": "9:35 AM",
    "start_date": "2026-05-26",
    "location": "Main Campus",
    "campus": "MC",
    "mode": "in-person",
    "instructor": "Price, A",
    "seats_open": 0,
    "seats_total": 10,
    "prerequisite_text": null,
    "prerequisite_courses": []
  },
  {
    "college_code": "isothermal",
    "term": "2026SU",
    "course_prefix": "WLD",
    "course_number": "143",
    "course_title": "Welding Metallurgy",
    "credits": 2,
    "crn": "WLD-143-001T1",
    "days": "T Th",
    "start_time": "12:00 PM",
    "end_time": "12:48 PM",
    "start_date": "2026-05-26",
    "location": "Main Campus",
    "campus": "MC",
    "mode": "in-person",
    "instructor": "Price, A",
    "seats_open": 1,
    "seats_total": 10,
    "prerequisite_text": null,
    "prerequisite_courses": []
  },
  {
    "college_code": "isothermal",
    "term": "2026SU",
    "course_prefix": "WLD",
    "course_number": "215",
    "course_title": "SMAW (stick) Pipe",
    "credits": 4,
    "crn": "WLD-215-001T1",
    "days": "M W",
    "start_time": "7:30 AM",
    "end_time": "8:20 AM",
    "start_date": "2026-05-26",
    "location": "Main Campus",
    "campus": "MC",
    "mode": "in-person",
    "instructor": "Nelson, H",
    "seats_open": 3,
    "seats_total": 15,
    "prerequisite_text": null,
    "prerequisite_courses": []
  },
  {
    "college_code": "isothermal",
    "term": "2026SU",
    "course_prefix": "WOL",
    "course_number": "110",
    "course_title": "Basic Construction Skills",
    "credits": 3,
    "crn": "WOL-110-700I1",
    "days": "",
    "start_time": "",
    "end_time": "",
    "start_date": "2026-05-26",
    "location": "Main Campus",
    "campus": "MC",
    "mode": "online",
    "instructor": "Price, A",
    "seats_open": 12,
    "seats_total": 20,
    "prerequisite_text": null,
    "prerequisite_courses": []
  }
]
