[
  {
    "cipCode": "1101",
    "cipTitle": "Computer and Information Sciences, General",
    "credentialLevel": 1,
    "credentialTitle": "Undergraduate Certificate or Diploma",
    "awardsLevel1": 0,
    "awardsLevel2": 0,
    "earnings1YrMedian": null,
    "earnings5YrMedian": null,
    "earnings5YrPellMedian": null,
    "earnings5YrNonPellMedian": null,
    "earnings4YrMedianNational": null,
    "earnings4YrP25National": null,
    "earnings4YrP75National": null
  },
  {
    "cipCode": "1101",
    "cipTitle": "Computer and Information Sciences, General",
    "credentialLevel": 2,
    "credentialTitle": "Associate's Degree",
    "awardsLevel1": 0,
    "awardsLevel2": 0,
    "earnings1YrMedian": null,
    "earnings5YrMedian": null,
    "earnings5YrPellMedian": null,
    "earnings5YrNonPellMedian": null,
    "earnings4YrMedianNational": null,
    "earnings4YrP25National": null,
    "earnings4YrP75National": null
  },
  {
    "cipCode": "1204",
    "cipTitle": "Cosmetology and Related Personal Grooming Services",
    "credentialLevel": 1,
    "credentialTitle": "Undergraduate Certificate or Diploma",
    "awardsLevel1": 12,
    "awardsLevel2": 22,
    "earnings1YrMedian": null,
    "earnings5YrMedian": null,
    "earnings5YrPellMedian": null,
    "earnings5YrNonPellMedian": null,
    "earnings4YrMedianNational": 26307,
    "earnings4YrP25National": 13783,
    "earnings4YrP75National": 41270
  },
  {
    "cipCode": "1907",
    "cipTitle": "Human Development, Family Studies, and Related Services",
    "credentialLevel": 2,
    "credentialTitle": "Associate's Degree",
    "awardsLevel1": 0,
    "awardsLevel2": 0,
    "earnings1YrMedian": null,
    "earnings5YrMedian": null,
    "earnings5YrPellMedian": null,
    "earnings5YrNonPellMedian": null,
    "earnings4YrMedianNational": null,
    "earnings4YrP25National": null,
    "earnings4YrP75National": null
  },
  {
    "cipCode": "3099",
    "cipTitle": "Multi/Interdisciplinary Studies, Other",
    "credentialLevel": 2,
    "credentialTitle": "Associate's Degree",
    "awardsLevel1": 2,
    "awardsLevel2": 1,
    "earnings1YrMedian": null,
    "earnings5YrMedian": null,
    "earnings5YrPellMedian": null,
    "earnings5YrNonPellMedian": null,
    "earnings4YrMedianNational": null,
    "earnings4YrP25National": null,
    "earnings4YrP75National": null
  },
  {
    "cipCode": "4701",
    "cipTitle": "Electrical/Electronics Maintenance and Repair Technologies/Technicians",
    "credentialLevel": 1,
    "credentialTitle": "Undergraduate Certificate or Diploma",
    "awardsLevel1": 0,
    "awardsLevel2": 0,
    "earnings1YrMedian": null,
    "earnings5YrMedian": null,
    "earnings5YrPellMedian": null,
    "earnings5YrNonPellMedian": null,
    "earnings4YrMedianNational": 43027,
    "earnings4YrP25National": 23814,
    "earnings4YrP75National": 63052
  },
  {
    "cipCode": "4701",
    "cipTitle": "Electrical/Electronics Maintenance and Repair Technologies/Technicians",
    "credentialLevel": 2,
    "credentialTitle": "Associate's Degree",
    "awardsLevel1": 23,
    "awardsLevel2": 27,
    "earnings1YrMedian": 39940,
    "earnings5YrMedian": null,
    "earnings5YrPellMedian": null,
    "earnings5YrNonPellMedian": null,
    "earnings4YrMedianNational": 63241,
    "earnings4YrP25National": 42076,
    "earnings4YrP75National": 85887
  },
  {
    "cipCode": "4703",
    "cipTitle": "Heavy/Industrial Equipment Maintenance Technologies/Technicians",
    "credentialLevel": 1,
    "credentialTitle": "Undergraduate Certificate or Diploma",
    "awardsLevel1": 0,
    "awardsLevel2": 13,
    "earnings1YrMedian": null,
    "earnings5YrMedian": null,
    "earnings5YrPellMedian": null,
    "earnings5YrNonPellMedian": null,
    "earnings4YrMedianNational": 62199,
    "earnings4YrP25National": 41552,
    "earnings4YrP75National": 82622
  },
  {
    "cipCode": "4805",
    "cipTitle": "Precision Metal Working",
    "credentialLevel": 1,
    "credentialTitle": "Undergraduate Certificate or Diploma",
    "awardsLevel1": 9,
    "awardsLevel2": 17,
    "earnings1YrMedian": 24349,
    "earnings5YrMedian": null,
    "earnings5YrPellMedian": null,
    "earnings5YrNonPellMedian": null,
    "earnings4YrMedianNational": 48702,
    "earnings4YrP25National": 31475,
    "earnings4YrP75National": 65767
  },
  {
    "cipCode": "4805",
    "cipTitle": "Precision Metal Working",
    "credentialLevel": 2,
    "credentialTitle": "Associate's Degree",
    "awardsLevel1": null,
    "awardsLevel2": 0,
    "earnings1YrMedian": null,
    "earnings5YrMedian": null,
    "earnings5YrPellMedian": null,
    "earnings5YrNonPellMedian": null,
    "earnings4YrMedianNational": null,
    "earnings4YrP25National": null,
    "earnings4YrP75National": null
  },
  {
    "cipCode": "5108",
    "cipTitle": "Allied Health and Medical Assisting Services",
    "credentialLevel": 1,
    "credentialTitle": "Undergraduate Certificate or Diploma",
    "awardsLevel1": 0,
    "awardsLevel2": 5,
    "earnings1YrMedian": null,
    "earnings5YrMedian": null,
    "earnings5YrPellMedian": null,
    "earnings5YrNonPellMedian": null,
    "earnings4YrMedianNational": null,
    "earnings4YrP25National": null,
    "earnings4YrP75National": null
  },
  {
    "cipCode": "5139",
    "cipTitle": "Practical Nursing, Vocational Nursing and Nursing Assistants",
    "credentialLevel": 1,
    "credentialTitle": "Undergraduate Certificate or Diploma",
    "awardsLevel1": 46,
    "awardsLevel2": 38,
    "earnings1YrMedian": 44026,
    "earnings5YrMedian": 44296,
    "earnings5YrPellMedian": null,
    "earnings5YrNonPellMedian": null,
    "earnings4YrMedianNational": 56073,
    "earnings4YrP25National": 37200,
    "earnings4YrP75National": 76301
  },
  {
    "cipCode": "5199",
    "cipTitle": "Health Professions and Related Clinical Sciences, Other",
    "credentialLevel": 1,
    "credentialTitle": "Undergraduate Certificate or Diploma",
    "awardsLevel1": 23,
    "awardsLevel2": 8,
    "earnings1YrMedian": null,
    "earnings5YrMedian": null,
    "earnings5YrPellMedian": null,
    "earnings5YrNonPellMedian": null,
    "earnings4YrMedianNational": 46980,
    "earnings4YrP25National": 32859,
    "earnings4YrP75National": 66311
  },
  {
    "cipCode": "5204",
    "cipTitle": "Business Operations Support and Assistant Services",
    "credentialLevel": 2,
    "credentialTitle": "Associate's Degree",
    "awardsLevel1": 4,
    "awardsLevel2": 5,
    "earnings1YrMedian": null,
    "earnings5YrMedian": null,
    "earnings5YrPellMedian": null,
    "earnings5YrNonPellMedian": null,
    "earnings4YrMedianNational": 37587,
    "earnings4YrP25National": 25176,
    "earnings4YrP75National": 49668
  }
]
