[
  {
    "cipCode": "1002",
    "cipTitle": "Audiovisual Communications Technologies/Technicians",
    "credentialLevel": 1,
    "credentialTitle": "Undergraduate Certificate or Diploma",
    "awardsLevel1": 0,
    "awardsLevel2": 1,
    "earnings1YrMedian": null,
    "earnings5YrMedian": null,
    "earnings5YrPellMedian": null,
    "earnings5YrNonPellMedian": null,
    "earnings4YrMedianNational": 33223,
    "earnings4YrP25National": 17256,
    "earnings4YrP75National": 49724
  },
  {
    "cipCode": "1002",
    "cipTitle": "Audiovisual Communications Technologies/Technicians",
    "credentialLevel": 2,
    "credentialTitle": "Associate's Degree",
    "awardsLevel1": 14,
    "awardsLevel2": 6,
    "earnings1YrMedian": null,
    "earnings5YrMedian": null,
    "earnings5YrPellMedian": null,
    "earnings5YrNonPellMedian": null,
    "earnings4YrMedianNational": 35660,
    "earnings4YrP25National": 19601,
    "earnings4YrP75National": 50543
  },
  {
    "cipCode": "1101",
    "cipTitle": "Computer and Information Sciences, General",
    "credentialLevel": 1,
    "credentialTitle": "Undergraduate Certificate or Diploma",
    "awardsLevel1": 1,
    "awardsLevel2": 0,
    "earnings1YrMedian": null,
    "earnings5YrMedian": null,
    "earnings5YrPellMedian": null,
    "earnings5YrNonPellMedian": null,
    "earnings4YrMedianNational": 50984,
    "earnings4YrP25National": 31514,
    "earnings4YrP75National": 73655
  },
  {
    "cipCode": "1101",
    "cipTitle": "Computer and Information Sciences, General",
    "credentialLevel": 2,
    "credentialTitle": "Associate's Degree",
    "awardsLevel1": 41,
    "awardsLevel2": 24,
    "earnings1YrMedian": null,
    "earnings5YrMedian": 56958,
    "earnings5YrPellMedian": null,
    "earnings5YrNonPellMedian": null,
    "earnings4YrMedianNational": 54246,
    "earnings4YrP25National": 35954,
    "earnings4YrP75National": 76280
  },
  {
    "cipCode": "1102",
    "cipTitle": "Computer Programming",
    "credentialLevel": 1,
    "credentialTitle": "Undergraduate Certificate or Diploma",
    "awardsLevel1": 1,
    "awardsLevel2": 0,
    "earnings1YrMedian": null,
    "earnings5YrMedian": null,
    "earnings5YrPellMedian": null,
    "earnings5YrNonPellMedian": null,
    "earnings4YrMedianNational": 56556,
    "earnings4YrP25National": 35112,
    "earnings4YrP75National": 84410
  },
  {
    "cipCode": "1102",
    "cipTitle": "Computer Programming",
    "credentialLevel": 2,
    "credentialTitle": "Associate's Degree",
    "awardsLevel1": 0,
    "awardsLevel2": 0,
    "earnings1YrMedian": null,
    "earnings5YrMedian": null,
    "earnings5YrPellMedian": null,
    "earnings5YrNonPellMedian": null,
    "earnings4YrMedianNational": 58070,
    "earnings4YrP25National": 37249,
    "earnings4YrP75National": 83473
  },
  {
    "cipCode": "1108",
    "cipTitle": "Computer Software and Media Applications",
    "credentialLevel": 1,
    "credentialTitle": "Undergraduate Certificate or Diploma",
    "awardsLevel1": null,
    "awardsLevel2": null,
    "earnings1YrMedian": null,
    "earnings5YrMedian": null,
    "earnings5YrPellMedian": null,
    "earnings5YrNonPellMedian": null,
    "earnings4YrMedianNational": 41400,
    "earnings4YrP25National": 23342,
    "earnings4YrP75National": 64298
  },
  {
    "cipCode": "1109",
    "cipTitle": "Computer Systems Networking and Telecommunications",
    "credentialLevel": 1,
    "credentialTitle": "Undergraduate Certificate or Diploma",
    "awardsLevel1": 2,
    "awardsLevel2": 2,
    "earnings1YrMedian": null,
    "earnings5YrMedian": null,
    "earnings5YrPellMedian": null,
    "earnings5YrNonPellMedian": null,
    "earnings4YrMedianNational": 50162,
    "earnings4YrP25National": 33749,
    "earnings4YrP75National": 68140
  },
  {
    "cipCode": "1109",
    "cipTitle": "Computer Systems Networking and Telecommunications",
    "credentialLevel": 2,
    "credentialTitle": "Associate's Degree",
    "awardsLevel1": 0,
    "awardsLevel2": 0,
    "earnings1YrMedian": null,
    "earnings5YrMedian": null,
    "earnings5YrPellMedian": null,
    "earnings5YrNonPellMedian": null,
    "earnings4YrMedianNational": null,
    "earnings4YrP25National": null,
    "earnings4YrP75National": null
  },
  {
    "cipCode": "1110",
    "cipTitle": "Computer/Information Technology Administration and Management",
    "credentialLevel": 1,
    "credentialTitle": "Undergraduate Certificate or Diploma",
    "awardsLevel1": 0,
    "awardsLevel2": 0,
    "earnings1YrMedian": null,
    "earnings5YrMedian": null,
    "earnings5YrPellMedian": null,
    "earnings5YrNonPellMedian": null,
    "earnings4YrMedianNational": 52615,
    "earnings4YrP25National": 33200,
    "earnings4YrP75National": 75374
  },
  {
    "cipCode": "1110",
    "cipTitle": "Computer/Information Technology Administration and Management",
    "credentialLevel": 2,
    "credentialTitle": "Associate's Degree",
    "awardsLevel1": 8,
    "awardsLevel2": 14,
    "earnings1YrMedian": null,
    "earnings5YrMedian": null,
    "earnings5YrPellMedian": null,
    "earnings5YrNonPellMedian": null,
    "earnings4YrMedianNational": null,
    "earnings4YrP25National": null,
    "earnings4YrP75National": null
  },
  {
    "cipCode": "1199",
    "cipTitle": "Computer and Information Sciences and Support Services, Other",
    "credentialLevel": 1,
    "credentialTitle": "Undergraduate Certificate or Diploma",
    "awardsLevel1": 1,
    "awardsLevel2": 0,
    "earnings1YrMedian": null,
    "earnings5YrMedian": null,
    "earnings5YrPellMedian": null,
    "earnings5YrNonPellMedian": null,
    "earnings4YrMedianNational": 37083,
    "earnings4YrP25National": 20956,
    "earnings4YrP75National": 56487
  },
  {
    "cipCode": "1205",
    "cipTitle": "Culinary Arts and Related Services",
    "credentialLevel": 1,
    "credentialTitle": "Undergraduate Certificate or Diploma",
    "awardsLevel1": 4,
    "awardsLevel2": 5,
    "earnings1YrMedian": null,
    "earnings5YrMedian": null,
    "earnings5YrPellMedian": null,
    "earnings5YrNonPellMedian": null,
    "earnings4YrMedianNational": null,
    "earnings4YrP25National": null,
    "earnings4YrP75National": null
  },
  {
    "cipCode": "1312",
    "cipTitle": "Teacher Education and Professional Development, Specific Levels and Methods",
    "credentialLevel": 2,
    "credentialTitle": "Associate's Degree",
    "awardsLevel1": 28,
    "awardsLevel2": 13,
    "earnings1YrMedian": 28635,
    "earnings5YrMedian": 38208,
    "earnings5YrPellMedian": null,
    "earnings5YrNonPellMedian": null,
    "earnings4YrMedianNational": 37656,
    "earnings4YrP25National": 24793,
    "earnings4YrP75National": 49794
  },
  {
    "cipCode": "1313",
    "cipTitle": "Teacher Education and Professional Development, Specific Subject Areas",
    "credentialLevel": 1,
    "credentialTitle": "Undergraduate Certificate or Diploma",
    "awardsLevel1": 0,
    "awardsLevel2": 0,
    "earnings1YrMedian": null,
    "earnings5YrMedian": null,
    "earnings5YrPellMedian": null,
    "earnings5YrNonPellMedian": null,
    "earnings4YrMedianNational": 44570,
    "earnings4YrP25National": 29758,
    "earnings4YrP75National": 64283
  },
  {
    "cipCode": "1503",
    "cipTitle": "Electrical/Electronic Engineering Technologies/Technicians",
    "credentialLevel": 2,
    "credentialTitle": "Associate's Degree",
    "awardsLevel1": 0,
    "awardsLevel2": 1,
    "earnings1YrMedian": null,
    "earnings5YrMedian": null,
    "earnings5YrPellMedian": null,
    "earnings5YrNonPellMedian": null,
    "earnings4YrMedianNational": null,
    "earnings4YrP25National": null,
    "earnings4YrP75National": null
  },
  {
    "cipCode": "1504",
    "cipTitle": "Electromechanical Technologies/Technicians",
    "credentialLevel": 1,
    "credentialTitle": "Undergraduate Certificate or Diploma",
    "awardsLevel1": 23,
    "awardsLevel2": 3,
    "earnings1YrMedian": null,
    "earnings5YrMedian": null,
    "earnings5YrPellMedian": null,
    "earnings5YrNonPellMedian": null,
    "earnings4YrMedianNational": 65202,
    "earnings4YrP25National": 42000,
    "earnings4YrP75National": 87712
  },
  {
    "cipCode": "1504",
    "cipTitle": "Electromechanical Technologies/Technicians",
    "credentialLevel": 2,
    "credentialTitle": "Associate's Degree",
    "awardsLevel1": 0,
    "awardsLevel2": 0,
    "earnings1YrMedian": null,
    "earnings5YrMedian": null,
    "earnings5YrPellMedian": null,
    "earnings5YrNonPellMedian": null,
    "earnings4YrMedianNational": null,
    "earnings4YrP25National": null,
    "earnings4YrP75National": null
  },
  {
    "cipCode": "1506",
    "cipTitle": "Industrial Production Technologies/Technicians",
    "credentialLevel": 2,
    "credentialTitle": "Associate's Degree",
    "awardsLevel1": 0,
    "awardsLevel2": 0,
    "earnings1YrMedian": null,
    "earnings5YrMedian": null,
    "earnings5YrPellMedian": null,
    "earnings5YrNonPellMedian": null,
    "earnings4YrMedianNational": null,
    "earnings4YrP25National": null,
    "earnings4YrP75National": null
  },
  {
    "cipCode": "1512",
    "cipTitle": "Computer Engineering Technologies/Technicians",
    "credentialLevel": 2,
    "credentialTitle": "Associate's Degree",
    "awardsLevel1": 0,
    "awardsLevel2": 0,
    "earnings1YrMedian": null,
    "earnings5YrMedian": null,
    "earnings5YrPellMedian": null,
    "earnings5YrNonPellMedian": null,
    "earnings4YrMedianNational": 55195,
    "earnings4YrP25National": 38727,
    "earnings4YrP75National": 74024
  },
  {
    "cipCode": "1513",
    "cipTitle": "Drafting/Design Engineering Technologies/Technicians",
    "credentialLevel": 1,
    "credentialTitle": "Undergraduate Certificate or Diploma",
    "awardsLevel1": 3,
    "awardsLevel2": 13,
    "earnings1YrMedian": null,
    "earnings5YrMedian": null,
    "earnings5YrPellMedian": null,
    "earnings5YrNonPellMedian": null,
    "earnings4YrMedianNational": 53359,
    "earnings4YrP25National": 35073,
    "earnings4YrP75National": 68539
  },
  {
    "cipCode": "1599",
    "cipTitle": "Engineering/Engineering-Related Technologies/Technicians, Other",
    "credentialLevel": 2,
    "credentialTitle": "Associate's Degree",
    "awardsLevel1": 15,
    "awardsLevel2": 23,
    "earnings1YrMedian": null,
    "earnings5YrMedian": 81023,
    "earnings5YrPellMedian": null,
    "earnings5YrNonPellMedian": null,
    "earnings4YrMedianNational": 69455,
    "earnings4YrP25National": 48924,
    "earnings4YrP75National": 94743
  },
  {
    "cipCode": "1616",
    "cipTitle": "American Sign Language",
    "credentialLevel": 1,
    "credentialTitle": "Undergraduate Certificate or Diploma",
    "awardsLevel1": 9,
    "awardsLevel2": 12,
    "earnings1YrMedian": null,
    "earnings5YrMedian": null,
    "earnings5YrPellMedian": null,
    "earnings5YrNonPellMedian": null,
    "earnings4YrMedianNational": 41771,
    "earnings4YrP25National": 25434,
    "earnings4YrP75National": 57857
  },
  {
    "cipCode": "1616",
    "cipTitle": "American Sign Language",
    "credentialLevel": 2,
    "credentialTitle": "Associate's Degree",
    "awardsLevel1": 2,
    "awardsLevel2": 3,
    "earnings1YrMedian": null,
    "earnings5YrMedian": null,
    "earnings5YrPellMedian": null,
    "earnings5YrNonPellMedian": null,
    "earnings4YrMedianNational": 37886,
    "earnings4YrP25National": 23705,
    "earnings4YrP75National": 50828
  },
  {
    "cipCode": "1907",
    "cipTitle": "Human Development, Family Studies, and Related Services",
    "credentialLevel": 1,
    "credentialTitle": "Undergraduate Certificate or Diploma",
    "awardsLevel1": 4,
    "awardsLevel2": 5,
    "earnings1YrMedian": null,
    "earnings5YrMedian": null,
    "earnings5YrPellMedian": null,
    "earnings5YrNonPellMedian": null,
    "earnings4YrMedianNational": null,
    "earnings4YrP25National": null,
    "earnings4YrP75National": null
  },
  {
    "cipCode": "2203",
    "cipTitle": "Legal Support Services",
    "credentialLevel": 1,
    "credentialTitle": "Undergraduate Certificate or Diploma",
    "awardsLevel1": 0,
    "awardsLevel2": 0,
    "earnings1YrMedian": null,
    "earnings5YrMedian": null,
    "earnings5YrPellMedian": null,
    "earnings5YrNonPellMedian": null,
    "earnings4YrMedianNational": null,
    "earnings4YrP25National": null,
    "earnings4YrP75National": null
  },
  {
    "cipCode": "2203",
    "cipTitle": "Legal Support Services",
    "credentialLevel": 2,
    "credentialTitle": "Associate's Degree",
    "awardsLevel1": 0,
    "awardsLevel2": 0,
    "earnings1YrMedian": null,
    "earnings5YrMedian": null,
    "earnings5YrPellMedian": null,
    "earnings5YrNonPellMedian": null,
    "earnings4YrMedianNational": null,
    "earnings4YrP25National": null,
    "earnings4YrP75National": null
  },
  {
    "cipCode": "2401",
    "cipTitle": "Liberal Arts and Sciences, General Studies and Humanities",
    "credentialLevel": 2,
    "credentialTitle": "Associate's Degree",
    "awardsLevel1": 96,
    "awardsLevel2": 89,
    "earnings1YrMedian": 31549,
    "earnings5YrMedian": 43911,
    "earnings5YrPellMedian": 40467,
    "earnings5YrNonPellMedian": 46508,
    "earnings4YrMedianNational": 44125,
    "earnings4YrP25National": 28893,
    "earnings4YrP75National": 61611
  },
  {
    "cipCode": "2601",
    "cipTitle": "Biology, General",
    "credentialLevel": 2,
    "credentialTitle": "Associate's Degree",
    "awardsLevel1": 17,
    "awardsLevel2": 7,
    "earnings1YrMedian": null,
    "earnings5YrMedian": null,
    "earnings5YrPellMedian": null,
    "earnings5YrNonPellMedian": null,
    "earnings4YrMedianNational": 44758,
    "earnings4YrP25National": 27517,
    "earnings4YrP75National": 65127
  },
  {
    "cipCode": "3001",
    "cipTitle": "Biological and Physical Sciences",
    "credentialLevel": 2,
    "credentialTitle": "Associate's Degree",
    "awardsLevel1": 2,
    "awardsLevel2": 1,
    "earnings1YrMedian": null,
    "earnings5YrMedian": null,
    "earnings5YrPellMedian": null,
    "earnings5YrNonPellMedian": null,
    "earnings4YrMedianNational": 50181,
    "earnings4YrP25National": 32493,
    "earnings4YrP75National": 73808
  },
  {
    "cipCode": "3105",
    "cipTitle": "Sports, Kinesiology, and Physical Education/Fitness",
    "credentialLevel": 2,
    "credentialTitle": "Associate's Degree",
    "awardsLevel1": 6,
    "awardsLevel2": 2,
    "earnings1YrMedian": null,
    "earnings5YrMedian": null,
    "earnings5YrPellMedian": null,
    "earnings5YrNonPellMedian": null,
    "earnings4YrMedianNational": 40162,
    "earnings4YrP25National": 25186,
    "earnings4YrP75National": 56550
  },
  {
    "cipCode": "4103",
    "cipTitle": "Physical Science Technologies/Technicians",
    "credentialLevel": 2,
    "credentialTitle": "Associate's Degree",
    "awardsLevel1": 8,
    "awardsLevel2": 6,
    "earnings1YrMedian": null,
    "earnings5YrMedian": null,
    "earnings5YrPellMedian": null,
    "earnings5YrNonPellMedian": null,
    "earnings4YrMedianNational": 80768,
    "earnings4YrP25National": 51052,
    "earnings4YrP75National": 132357
  },
  {
    "cipCode": "4301",
    "cipTitle": "Criminal Justice and Corrections",
    "credentialLevel": 1,
    "credentialTitle": "Undergraduate Certificate or Diploma",
    "awardsLevel1": 8,
    "awardsLevel2": 13,
    "earnings1YrMedian": null,
    "earnings5YrMedian": null,
    "earnings5YrPellMedian": null,
    "earnings5YrNonPellMedian": null,
    "earnings4YrMedianNational": 57702,
    "earnings4YrP25National": 39878,
    "earnings4YrP75National": 76285
  },
  {
    "cipCode": "4301",
    "cipTitle": "Criminal Justice and Corrections",
    "credentialLevel": 2,
    "credentialTitle": "Associate's Degree",
    "awardsLevel1": 23,
    "awardsLevel2": 25,
    "earnings1YrMedian": 39426,
    "earnings5YrMedian": 48911,
    "earnings5YrPellMedian": null,
    "earnings5YrNonPellMedian": null,
    "earnings4YrMedianNational": 46706,
    "earnings4YrP25National": 31475,
    "earnings4YrP75National": 63659
  },
  {
    "cipCode": "4302",
    "cipTitle": "Fire Protection",
    "credentialLevel": 2,
    "credentialTitle": "Associate's Degree",
    "awardsLevel1": 0,
    "awardsLevel2": 0,
    "earnings1YrMedian": null,
    "earnings5YrMedian": null,
    "earnings5YrPellMedian": null,
    "earnings5YrNonPellMedian": null,
    "earnings4YrMedianNational": null,
    "earnings4YrP25National": null,
    "earnings4YrP75National": null
  },
  {
    "cipCode": "4304",
    "cipTitle": "Security Science and Technology",
    "credentialLevel": 1,
    "credentialTitle": "Undergraduate Certificate or Diploma",
    "awardsLevel1": null,
    "awardsLevel2": null,
    "earnings1YrMedian": null,
    "earnings5YrMedian": null,
    "earnings5YrPellMedian": null,
    "earnings5YrNonPellMedian": null,
    "earnings4YrMedianNational": 54296,
    "earnings4YrP25National": 36542,
    "earnings4YrP75National": 76637
  },
  {
    "cipCode": "4407",
    "cipTitle": "Social Work",
    "credentialLevel": 2,
    "credentialTitle": "Associate's Degree",
    "awardsLevel1": 0,
    "awardsLevel2": 0,
    "earnings1YrMedian": null,
    "earnings5YrMedian": null,
    "earnings5YrPellMedian": null,
    "earnings5YrNonPellMedian": null,
    "earnings4YrMedianNational": null,
    "earnings4YrP25National": null,
    "earnings4YrP75National": null
  },
  {
    "cipCode": "5001",
    "cipTitle": "Visual and Performing Arts, General",
    "credentialLevel": 2,
    "credentialTitle": "Associate's Degree",
    "awardsLevel1": 0,
    "awardsLevel2": 0,
    "earnings1YrMedian": null,
    "earnings5YrMedian": 29828,
    "earnings5YrPellMedian": null,
    "earnings5YrNonPellMedian": null,
    "earnings4YrMedianNational": null,
    "earnings4YrP25National": null,
    "earnings4YrP75National": null
  },
  {
    "cipCode": "5004",
    "cipTitle": "Design and Applied Arts",
    "credentialLevel": 1,
    "credentialTitle": "Undergraduate Certificate or Diploma",
    "awardsLevel1": 0,
    "awardsLevel2": 0,
    "earnings1YrMedian": null,
    "earnings5YrMedian": null,
    "earnings5YrPellMedian": null,
    "earnings5YrNonPellMedian": null,
    "earnings4YrMedianNational": null,
    "earnings4YrP25National": null,
    "earnings4YrP75National": null
  },
  {
    "cipCode": "5004",
    "cipTitle": "Design and Applied Arts",
    "credentialLevel": 2,
    "credentialTitle": "Associate's Degree",
    "awardsLevel1": 0,
    "awardsLevel2": 0,
    "earnings1YrMedian": null,
    "earnings5YrMedian": null,
    "earnings5YrPellMedian": null,
    "earnings5YrNonPellMedian": null,
    "earnings4YrMedianNational": 38127,
    "earnings4YrP25National": 22789,
    "earnings4YrP75National": 53862
  },
  {
    "cipCode": "5007",
    "cipTitle": "Fine and Studio Arts",
    "credentialLevel": 2,
    "credentialTitle": "Associate's Degree",
    "awardsLevel1": 13,
    "awardsLevel2": 12,
    "earnings1YrMedian": null,
    "earnings5YrMedian": null,
    "earnings5YrPellMedian": null,
    "earnings5YrNonPellMedian": null,
    "earnings4YrMedianNational": 31650,
    "earnings4YrP25National": 18320,
    "earnings4YrP75National": 44432
  },
  {
    "cipCode": "5100",
    "cipTitle": "Health Services/Allied Health/Health Sciences, General",
    "credentialLevel": 2,
    "credentialTitle": "Associate's Degree",
    "awardsLevel1": 14,
    "awardsLevel2": 7,
    "earnings1YrMedian": 50389,
    "earnings5YrMedian": 35662,
    "earnings5YrPellMedian": null,
    "earnings5YrNonPellMedian": null,
    "earnings4YrMedianNational": 51180,
    "earnings4YrP25National": 35101,
    "earnings4YrP75National": 72128
  },
  {
    "cipCode": "5106",
    "cipTitle": "Dental Support Services and Allied Professions",
    "credentialLevel": 1,
    "credentialTitle": "Undergraduate Certificate or Diploma",
    "awardsLevel1": 9,
    "awardsLevel2": 9,
    "earnings1YrMedian": null,
    "earnings5YrMedian": 45610,
    "earnings5YrPellMedian": null,
    "earnings5YrNonPellMedian": null,
    "earnings4YrMedianNational": 33673,
    "earnings4YrP25National": 21167,
    "earnings4YrP75National": 43924
  },
  {
    "cipCode": "5107",
    "cipTitle": "Health and Medical Administrative Services",
    "credentialLevel": 1,
    "credentialTitle": "Undergraduate Certificate or Diploma",
    "awardsLevel1": 17,
    "awardsLevel2": 5,
    "earnings1YrMedian": 37514,
    "earnings5YrMedian": 41559,
    "earnings5YrPellMedian": null,
    "earnings5YrNonPellMedian": null,
    "earnings4YrMedianNational": 35447,
    "earnings4YrP25National": 21575,
    "earnings4YrP75National": 46852
  },
  {
    "cipCode": "5107",
    "cipTitle": "Health and Medical Administrative Services",
    "credentialLevel": 2,
    "credentialTitle": "Associate's Degree",
    "awardsLevel1": 0,
    "awardsLevel2": 0,
    "earnings1YrMedian": null,
    "earnings5YrMedian": null,
    "earnings5YrPellMedian": null,
    "earnings5YrNonPellMedian": null,
    "earnings4YrMedianNational": null,
    "earnings4YrP25National": null,
    "earnings4YrP75National": null
  },
  {
    "cipCode": "5108",
    "cipTitle": "Allied Health and Medical Assisting Services",
    "credentialLevel": 1,
    "credentialTitle": "Undergraduate Certificate or Diploma",
    "awardsLevel1": 28,
    "awardsLevel2": 28,
    "earnings1YrMedian": 38885,
    "earnings5YrMedian": 41894,
    "earnings5YrPellMedian": null,
    "earnings5YrNonPellMedian": null,
    "earnings4YrMedianNational": 34272,
    "earnings4YrP25National": 21209,
    "earnings4YrP75National": 44441
  },
  {
    "cipCode": "5109",
    "cipTitle": "Allied Health Diagnostic, Intervention, and Treatment Professions",
    "credentialLevel": 1,
    "credentialTitle": "Undergraduate Certificate or Diploma",
    "awardsLevel1": 1,
    "awardsLevel2": 1,
    "earnings1YrMedian": null,
    "earnings5YrMedian": null,
    "earnings5YrPellMedian": null,
    "earnings5YrNonPellMedian": null,
    "earnings4YrMedianNational": 57584,
    "earnings4YrP25National": 37331,
    "earnings4YrP75National": 79965
  },
  {
    "cipCode": "5109",
    "cipTitle": "Allied Health Diagnostic, Intervention, and Treatment Professions",
    "credentialLevel": 2,
    "credentialTitle": "Associate's Degree",
    "awardsLevel1": 27,
    "awardsLevel2": 24,
    "earnings1YrMedian": 67610,
    "earnings5YrMedian": 73608,
    "earnings5YrPellMedian": 74961,
    "earnings5YrNonPellMedian": 70534,
    "earnings4YrMedianNational": 65389,
    "earnings4YrP25National": 46431,
    "earnings4YrP75National": 84999
  },
  {
    "cipCode": "5110",
    "cipTitle": "Clinical/Medical Laboratory Science/Research and Allied Professions",
    "credentialLevel": 1,
    "credentialTitle": "Undergraduate Certificate or Diploma",
    "awardsLevel1": 13,
    "awardsLevel2": 14,
    "earnings1YrMedian": null,
    "earnings5YrMedian": 37538,
    "earnings5YrPellMedian": null,
    "earnings5YrNonPellMedian": null,
    "earnings4YrMedianNational": 38675,
    "earnings4YrP25National": 25627,
    "earnings4YrP75National": 53775
  },
  {
    "cipCode": "5110",
    "cipTitle": "Clinical/Medical Laboratory Science/Research and Allied Professions",
    "credentialLevel": 2,
    "credentialTitle": "Associate's Degree",
    "awardsLevel1": 1,
    "awardsLevel2": 0,
    "earnings1YrMedian": null,
    "earnings5YrMedian": null,
    "earnings5YrPellMedian": null,
    "earnings5YrNonPellMedian": null,
    "earnings4YrMedianNational": 57472,
    "earnings4YrP25National": 43453,
    "earnings4YrP75National": 72106
  },
  {
    "cipCode": "5115",
    "cipTitle": "Mental and Social Health Services and Allied Professions",
    "credentialLevel": 1,
    "credentialTitle": "Undergraduate Certificate or Diploma",
    "awardsLevel1": 29,
    "awardsLevel2": 28,
    "earnings1YrMedian": 27799,
    "earnings5YrMedian": 38653,
    "earnings5YrPellMedian": null,
    "earnings5YrNonPellMedian": null,
    "earnings4YrMedianNational": 43365,
    "earnings4YrP25National": 27298,
    "earnings4YrP75National": 59932
  },
  {
    "cipCode": "5115",
    "cipTitle": "Mental and Social Health Services and Allied Professions",
    "credentialLevel": 2,
    "credentialTitle": "Associate's Degree",
    "awardsLevel1": 32,
    "awardsLevel2": 25,
    "earnings1YrMedian": null,
    "earnings5YrMedian": 36942,
    "earnings5YrPellMedian": null,
    "earnings5YrNonPellMedian": null,
    "earnings4YrMedianNational": 40734,
    "earnings4YrP25National": 26005,
    "earnings4YrP75National": 53366
  },
  {
    "cipCode": "5118",
    "cipTitle": "Ophthalmic and Optometric Support Services and Allied Professions",
    "credentialLevel": 1,
    "credentialTitle": "Undergraduate Certificate or Diploma",
    "awardsLevel1": null,
    "awardsLevel2": null,
    "earnings1YrMedian": null,
    "earnings5YrMedian": null,
    "earnings5YrPellMedian": null,
    "earnings5YrNonPellMedian": null,
    "earnings4YrMedianNational": 38061,
    "earnings4YrP25National": 23624,
    "earnings4YrP75National": 48445
  },
  {
    "cipCode": "5122",
    "cipTitle": "Public Health",
    "credentialLevel": 1,
    "credentialTitle": "Undergraduate Certificate or Diploma",
    "awardsLevel1": 10,
    "awardsLevel2": 6,
    "earnings1YrMedian": null,
    "earnings5YrMedian": null,
    "earnings5YrPellMedian": null,
    "earnings5YrNonPellMedian": null,
    "earnings4YrMedianNational": 53933,
    "earnings4YrP25National": 37480,
    "earnings4YrP75National": 76652
  },
  {
    "cipCode": "5133",
    "cipTitle": "Alternative and Complementary Medicine and Medical Systems",
    "credentialLevel": 1,
    "credentialTitle": "Undergraduate Certificate or Diploma",
    "awardsLevel1": 18,
    "awardsLevel2": 11,
    "earnings1YrMedian": 49459,
    "earnings5YrMedian": null,
    "earnings5YrPellMedian": null,
    "earnings5YrNonPellMedian": null,
    "earnings4YrMedianNational": 36403,
    "earnings4YrP25National": 14798,
    "earnings4YrP75National": 58443
  },
  {
    "cipCode": "5138",
    "cipTitle": "Registered Nursing, Nursing Administration, Nursing Research and Clinical Nursing",
    "credentialLevel": 2,
    "credentialTitle": "Associate's Degree",
    "awardsLevel1": 27,
    "awardsLevel2": 18,
    "earnings1YrMedian": 74427,
    "earnings5YrMedian": 85914,
    "earnings5YrPellMedian": null,
    "earnings5YrNonPellMedian": null,
    "earnings4YrMedianNational": 80813,
    "earnings4YrP25National": 61109,
    "earnings4YrP75National": 103839
  },
  {
    "cipCode": "5139",
    "cipTitle": "Practical Nursing, Vocational Nursing and Nursing Assistants",
    "credentialLevel": 1,
    "credentialTitle": "Undergraduate Certificate or Diploma",
    "awardsLevel1": 18,
    "awardsLevel2": 23,
    "earnings1YrMedian": 50770,
    "earnings5YrMedian": null,
    "earnings5YrPellMedian": null,
    "earnings5YrNonPellMedian": null,
    "earnings4YrMedianNational": 56073,
    "earnings4YrP25National": 37200,
    "earnings4YrP75National": 76301
  },
  {
    "cipCode": "5201",
    "cipTitle": "Business/Commerce, General",
    "credentialLevel": 2,
    "credentialTitle": "Associate's Degree",
    "awardsLevel1": 65,
    "awardsLevel2": 63,
    "earnings1YrMedian": null,
    "earnings5YrMedian": 58679,
    "earnings5YrPellMedian": null,
    "earnings5YrNonPellMedian": null,
    "earnings4YrMedianNational": 49927,
    "earnings4YrP25National": 33112,
    "earnings4YrP75National": 69450
  },
  {
    "cipCode": "5202",
    "cipTitle": "Business Administration, Management and Operations",
    "credentialLevel": 2,
    "credentialTitle": "Associate's Degree",
    "awardsLevel1": 22,
    "awardsLevel2": 24,
    "earnings1YrMedian": 46439,
    "earnings5YrMedian": null,
    "earnings5YrPellMedian": null,
    "earnings5YrNonPellMedian": null,
    "earnings4YrMedianNational": 48733,
    "earnings4YrP25National": 31704,
    "earnings4YrP75National": 67604
  },
  {
    "cipCode": "5203",
    "cipTitle": "Accounting and Related Services",
    "credentialLevel": 2,
    "credentialTitle": "Associate's Degree",
    "awardsLevel1": 7,
    "awardsLevel2": 13,
    "earnings1YrMedian": 37960,
    "earnings5YrMedian": 61448,
    "earnings5YrPellMedian": null,
    "earnings5YrNonPellMedian": null,
    "earnings4YrMedianNational": 47660,
    "earnings4YrP25National": 32411,
    "earnings4YrP75National": 63692
  },
  {
    "cipCode": "5204",
    "cipTitle": "Business Operations Support and Assistant Services",
    "credentialLevel": 2,
    "credentialTitle": "Associate's Degree",
    "awardsLevel1": 0,
    "awardsLevel2": 0,
    "earnings1YrMedian": null,
    "earnings5YrMedian": null,
    "earnings5YrPellMedian": null,
    "earnings5YrNonPellMedian": null,
    "earnings4YrMedianNational": null,
    "earnings4YrP25National": null,
    "earnings4YrP75National": null
  },
  {
    "cipCode": "5209",
    "cipTitle": "Hospitality Administration/Management",
    "credentialLevel": 2,
    "credentialTitle": "Associate's Degree",
    "awardsLevel1": 2,
    "awardsLevel2": 1,
    "earnings1YrMedian": null,
    "earnings5YrMedian": null,
    "earnings5YrPellMedian": null,
    "earnings5YrNonPellMedian": null,
    "earnings4YrMedianNational": null,
    "earnings4YrP25National": null,
    "earnings4YrP75National": null
  }
]
